[
{
 "price": 0.9627,
 "date": "2022-01-04"
},
{
 "price": 0.96,
 "date": "2022-01-05"
},
{
 "price": 0.9601,
 "date": "2022-01-06"
},
{
 "price": 0.9575,
 "date": "2022-01-07"
},
{
 "price": 0.9579,
 "date": "2022-01-10"
},
{
 "price": 0.9571,
 "date": "2022-01-11"
},
{
 "price": 0.9574,
 "date": "2022-01-12"
},
{
 "price": 0.9578,
 "date": "2022-01-13"
},
{
 "price": 0.9589,
 "date": "2022-01-14"
},
{
 "price": 0.9593,
 "date": "2022-01-17"
},
{
 "price": 0.9592,
 "date": "2022-01-18"
},
{
 "price": 0.9593,
 "date": "2022-01-19"
},
{
 "price": 0.959,
 "date": "2022-01-20"
},
{
 "price": 0.9578,
 "date": "2022-01-21"
},
{
 "price": 0.9586,
 "date": "2022-01-24"
},
{
 "price": 0.9588,
 "date": "2022-01-25"
},
{
 "price": 0.9589,
 "date": "2022-01-26"
},
{
 "price": 0.9572,
 "date": "2022-01-27"
},
{
 "price": 0.9574,
 "date": "2022-01-28"
},
{
 "price": 0.9576,
 "date": "2022-01-31"
},
{
 "price": 0.9577,
 "date": "2022-02-01"
},
{
 "price": 0.9578,
 "date": "2022-02-02"
},
{
 "price": 0.9578,
 "date": "2022-02-03"
},
{
 "price": 0.9574,
 "date": "2022-02-04"
},
{
 "price": 0.9578,
 "date": "2022-02-07"
},
{
 "price": 0.9558,
 "date": "2022-02-08"
},
{
 "price": 0.9561,
 "date": "2022-02-09"
},
{
 "price": 0.9563,
 "date": "2022-02-10"
},
{
 "price": 0.957,
 "date": "2022-02-11"
},
{
 "price": 0.9574,
 "date": "2022-02-14"
},
{
 "price": 0.9575,
 "date": "2022-02-15"
},
{
 "price": 0.9576,
 "date": "2022-02-16"
},
{
 "price": 0.9573,
 "date": "2022-02-17"
},
{
 "price": 0.9573,
 "date": "2022-02-18"
},
{
 "price": 0.9571,
 "date": "2022-02-21"
},
{
 "price": 0.9573,
 "date": "2022-02-22"
},
{
 "price": 0.9574,
 "date": "2022-02-23"
},
{
 "price": 0.9559,
 "date": "2022-02-25"
},
{
 "price": 0.9563,
 "date": "2022-02-28"
},
{
 "price": 0.9555,
 "date": "2022-03-01"
},
{
 "price": 0.9543,
 "date": "2022-03-02"
},
{
 "price": 0.9544,
 "date": "2022-03-03"
},
{
 "price": 0.9529,
 "date": "2022-03-04"
},
{
 "price": 0.9532,
 "date": "2022-03-07"
},
{
 "price": 0.9535,
 "date": "2022-03-08"
},
{
 "price": 0.9525,
 "date": "2022-03-09"
},
{
 "price": 0.9505,
 "date": "2022-03-10"
},
{
 "price": 0.9507,
 "date": "2022-03-11"
},
{
 "price": 0.9518,
 "date": "2022-03-16"
},
{
 "price": 0.9523,
 "date": "2022-03-17"
},
{
 "price": 0.9525,
 "date": "2022-03-18"
},
{
 "price": 0.953,
 "date": "2022-03-21"
},
{
 "price": 0.9531,
 "date": "2022-03-22"
},
{
 "price": 0.9531,
 "date": "2022-03-23"
},
{
 "price": 0.9527,
 "date": "2022-03-24"
},
{
 "price": 0.9529,
 "date": "2022-03-25"
},
{
 "price": 0.9531,
 "date": "2022-03-26"
},
{
 "price": 0.9533,
 "date": "2022-03-28"
},
{
 "price": 0.9536,
 "date": "2022-03-29"
},
{
 "price": 0.9537,
 "date": "2022-03-30"
},
{
 "price": 0.9539,
 "date": "2022-03-31"
},
{
 "price": 0.954,
 "date": "2022-04-01"
},
{
 "price": 0.9547,
 "date": "2022-04-04"
},
{
 "price": 0.9556,
 "date": "2022-04-05"
},
{
 "price": 0.9559,
 "date": "2022-04-06"
},
{
 "price": 0.9559,
 "date": "2022-04-07"
},
{
 "price": 0.9545,
 "date": "2022-04-08"
},
{
 "price": 0.9553,
 "date": "2022-04-11"
},
{
 "price": 0.9555,
 "date": "2022-04-12"
},
{
 "price": 0.9557,
 "date": "2022-04-13"
},
{
 "price": 0.9562,
 "date": "2022-04-14"
},
{
 "price": 0.9579,
 "date": "2022-04-19"
},
{
 "price": 0.9568,
 "date": "2022-04-20"
},
{
 "price": 0.9573,
 "date": "2022-04-21"
},
{
 "price": 0.958,
 "date": "2022-04-22"
},
{
 "price": 0.9576,
 "date": "2022-04-25"
},
{
 "price": 0.9578,
 "date": "2022-04-26"
},
{
 "price": 0.958,
 "date": "2022-04-27"
},
{
 "price": 0.9581,
 "date": "2022-04-28"
},
{
 "price": 0.9581,
 "date": "2022-04-29"
},
{
 "price": 0.9585,
 "date": "2022-05-02"
},
{
 "price": 0.9583,
 "date": "2022-05-03"
},
{
 "price": 0.9585,
 "date": "2022-05-04"
},
{
 "price": 0.9584,
 "date": "2022-05-05"
},
{
 "price": 0.9585,
 "date": "2022-05-06"
},
{
 "price": 0.959,
 "date": "2022-05-09"
},
{
 "price": 0.9577,
 "date": "2022-05-10"
},
{
 "price": 0.9568,
 "date": "2022-05-11"
},
{
 "price": 0.957,
 "date": "2022-05-12"
},
{
 "price": 0.9574,
 "date": "2022-05-13"
},
{
 "price": 0.958,
 "date": "2022-05-16"
},
{
 "price": 0.9581,
 "date": "2022-05-17"
},
{
 "price": 0.9584,
 "date": "2022-05-18"
},
{
 "price": 0.9586,
 "date": "2022-05-19"
},
{
 "price": 0.9588,
 "date": "2022-05-20"
},
{
 "price": 0.9594,
 "date": "2022-05-23"
},
{
 "price": 0.9596,
 "date": "2022-05-24"
},
{
 "price": 0.9597,
 "date": "2022-05-25"
},
{
 "price": 0.96,
 "date": "2022-05-26"
},
{
 "price": 0.9599,
 "date": "2022-05-27"
},
{
 "price": 0.9605,
 "date": "2022-05-30"
},
{
 "price": 0.9598,
 "date": "2022-05-31"
},
{
 "price": 0.96,
 "date": "2022-06-01"
},
{
 "price": 0.9601,
 "date": "2022-06-02"
},
{
 "price": 0.9605,
 "date": "2022-06-03"
},
{
 "price": 0.9613,
 "date": "2022-06-07"
},
{
 "price": 0.9615,
 "date": "2022-06-08"
},
{
 "price": 0.9615,
 "date": "2022-06-09"
},
{
 "price": 0.9616,
 "date": "2022-06-10"
},
{
 "price": 0.9622,
 "date": "2022-06-13"
},
{
 "price": 0.9623,
 "date": "2022-06-14"
},
{
 "price": 0.9623,
 "date": "2022-06-15"
},
{
 "price": 0.9624,
 "date": "2022-06-16"
},
{
 "price": 0.9626,
 "date": "2022-06-17"
},
{
 "price": 0.9613,
 "date": "2022-06-20"
},
{
 "price": 0.9601,
 "date": "2022-06-21"
},
{
 "price": 0.96,
 "date": "2022-06-22"
},
{
 "price": 0.9615,
 "date": "2022-06-23"
},
{
 "price": 0.9617,
 "date": "2022-06-24"
},
{
 "price": 0.963,
 "date": "2022-06-27"
},
{
 "price": 0.9632,
 "date": "2022-06-28"
},
{
 "price": 0.9633,
 "date": "2022-06-29"
},
{
 "price": 0.9636,
 "date": "2022-06-30"
},
{
 "price": 0.9649,
 "date": "2022-07-01"
},
{
 "price": 0.9667,
 "date": "2022-07-04"
},
{
 "price": 0.9673,
 "date": "2022-07-05"
},
{
 "price": 0.9669,
 "date": "2022-07-06"
},
{
 "price": 0.9664,
 "date": "2022-07-07"
},
{
 "price": 0.9652,
 "date": "2022-07-08"
},
{
 "price": 0.9649,
 "date": "2022-07-11"
},
{
 "price": 0.9667,
 "date": "2022-07-12"
},
{
 "price": 0.9668,
 "date": "2022-07-13"
},
{
 "price": 0.9657,
 "date": "2022-07-14"
},
{
 "price": 0.9651,
 "date": "2022-07-15"
},
{
 "price": 0.9654,
 "date": "2022-07-18"
},
{
 "price": 0.9656,
 "date": "2022-07-19"
},
{
 "price": 0.963,
 "date": "2022-07-20"
},
{
 "price": 0.9632,
 "date": "2022-07-21"
},
{
 "price": 0.9635,
 "date": "2022-07-22"
},
{
 "price": 0.9644,
 "date": "2022-07-25"
},
{
 "price": 0.9647,
 "date": "2022-07-26"
},
{
 "price": 0.965,
 "date": "2022-07-27"
},
{
 "price": 0.9626,
 "date": "2022-07-28"
},
{
 "price": 0.9627,
 "date": "2022-07-29"
},
{
 "price": 0.9635,
 "date": "2022-08-01"
},
{
 "price": 0.9641,
 "date": "2022-08-02"
},
{
 "price": 0.9647,
 "date": "2022-08-03"
},
{
 "price": 0.9649,
 "date": "2022-08-04"
},
{
 "price": 0.965,
 "date": "2022-08-05"
},
{
 "price": 0.9659,
 "date": "2022-08-08"
},
{
 "price": 0.966,
 "date": "2022-08-09"
},
{
 "price": 0.9663,
 "date": "2022-08-10"
},
{
 "price": 0.9664,
 "date": "2022-08-11"
},
{
 "price": 0.967,
 "date": "2022-08-12"
},
{
 "price": 0.9681,
 "date": "2022-08-15"
},
{
 "price": 0.9688,
 "date": "2022-08-16"
},
{
 "price": 0.9687,
 "date": "2022-08-17"
},
{
 "price": 0.9687,
 "date": "2022-08-18"
},
{
 "price": 0.9691,
 "date": "2022-08-19"
},
{
 "price": 0.9701,
 "date": "2022-08-22"
},
{
 "price": 0.9703,
 "date": "2022-08-23"
},
{
 "price": 0.9706,
 "date": "2022-08-24"
},
{
 "price": 0.9708,
 "date": "2022-08-25"
},
{
 "price": 0.9723,
 "date": "2022-08-26"
},
{
 "price": 0.9731,
 "date": "2022-08-29"
},
{
 "price": 0.9732,
 "date": "2022-08-30"
},
{
 "price": 0.9731,
 "date": "2022-08-31"
},
{
 "price": 0.973,
 "date": "2022-09-01"
},
{
 "price": 0.9733,
 "date": "2022-09-02"
},
{
 "price": 0.9736,
 "date": "2022-09-05"
},
{
 "price": 0.9739,
 "date": "2022-09-06"
},
{
 "price": 0.9741,
 "date": "2022-09-07"
},
{
 "price": 0.9726,
 "date": "2022-09-08"
},
{
 "price": 0.9725,
 "date": "2022-09-09"
},
{
 "price": 0.9694,
 "date": "2022-09-12"
},
{
 "price": 0.9663,
 "date": "2022-09-13"
},
{
 "price": 0.9677,
 "date": "2022-09-14"
},
{
 "price": 0.9681,
 "date": "2022-09-15"
},
{
 "price": 0.9681,
 "date": "2022-09-16"
},
{
 "price": 0.969,
 "date": "2022-09-19"
},
{
 "price": 0.9698,
 "date": "2022-09-20"
},
{
 "price": 0.9703,
 "date": "2022-09-21"
},
{
 "price": 0.9693,
 "date": "2022-09-22"
},
{
 "price": 0.9696,
 "date": "2022-09-23"
},
{
 "price": 0.9706,
 "date": "2022-09-26"
},
{
 "price": 0.9708,
 "date": "2022-09-27"
},
{
 "price": 0.9728,
 "date": "2022-09-28"
},
{
 "price": 0.9732,
 "date": "2022-09-29"
},
{
 "price": 0.9726,
 "date": "2022-09-30"
},
{
 "price": 0.9728,
 "date": "2022-10-03"
},
{
 "price": 0.9723,
 "date": "2022-10-04"
},
{
 "price": 0.9728,
 "date": "2022-10-05"
},
{
 "price": 0.973,
 "date": "2022-10-06"
},
{
 "price": 0.9735,
 "date": "2022-10-07"
},
{
 "price": 0.9742,
 "date": "2022-10-10"
},
{
 "price": 0.9744,
 "date": "2022-10-11"
},
{
 "price": 0.9748,
 "date": "2022-10-12"
},
{
 "price": 0.9752,
 "date": "2022-10-13"
},
{
 "price": 0.9753,
 "date": "2022-10-14"
},
{
 "price": 0.9756,
 "date": "2022-10-15"
},
{
 "price": 0.976257,
 "date": "2022-10-17"
},
{
 "price": 0.976655,
 "date": "2022-10-18"
},
{
 "price": 0.977347,
 "date": "2022-10-19"
},
{
 "price": 0.977664,
 "date": "2022-10-20"
},
{
 "price": 0.979,
 "date": "2022-10-24"
},
{
 "price": 0.979436,
 "date": "2022-10-25"
},
{
 "price": 0.979785,
 "date": "2022-10-26"
},
{
 "price": 0.980066,
 "date": "2022-10-27"
},
{
 "price": 0.980446,
 "date": "2022-10-28"
},
{
 "price": 0.98202,
 "date": "2022-11-02"
},
{
 "price": 0.982306,
 "date": "2022-11-03"
},
{
 "price": 0.982579,
 "date": "2022-11-04"
},
{
 "price": 0.98364,
 "date": "2022-11-07"
},
{
 "price": 0.98418,
 "date": "2022-11-09"
},
{
 "price": 0.984803,
 "date": "2022-11-11"
},
{
 "price": 0.985676,
 "date": "2022-11-14"
},
{
 "price": 0.986113,
 "date": "2022-11-15"
},
{
 "price": 0.98591,
 "date": "2022-11-16"
},
{
 "price": 0.986196,
 "date": "2022-11-17"
},
{
 "price": 0.986528,
 "date": "2022-11-18"
},
{
 "price": 0.987576,
 "date": "2022-11-21"
},
{
 "price": 0.988826,
 "date": "2022-11-22"
},
{
 "price": 0.989057,
 "date": "2022-11-23"
},
{
 "price": 0.989265,
 "date": "2022-11-24"
},
{
 "price": 0.989577,
 "date": "2022-11-25"
},
{
 "price": 0.990483,
 "date": "2022-11-28"
},
{
 "price": 0.990552,
 "date": "2022-11-29"
},
{
 "price": 0.990868,
 "date": "2022-11-30"
},
{
 "price": 0.991191,
 "date": "2022-12-01"
},
{
 "price": 0.992366,
 "date": "2022-12-05"
},
{
 "price": 0.99269,
 "date": "2022-12-06"
},
{
 "price": 0.99302,
 "date": "2022-12-07"
},
{
 "price": 0.99329,
 "date": "2022-12-08"
},
{
 "price": 0.993576,
 "date": "2022-12-09"
},
{
 "price": 0.994559,
 "date": "2022-12-12"
},
{
 "price": 0.994922,
 "date": "2022-12-13"
},
{
 "price": 0.995255,
 "date": "2022-12-14"
},
{
 "price": 0.995599,
 "date": "2022-12-15"
},
{
 "price": 0.995917,
 "date": "2022-12-16"
},
{
 "price": 0.996927,
 "date": "2022-12-19"
},
{
 "price": 0.997267,
 "date": "2022-12-20"
},
{
 "price": 0.997604,
 "date": "2022-12-21"
},
{
 "price": 0.997946,
 "date": "2022-12-22"
},
{
"price": 1.0,
"date": "2022-12-28"
},
{
"price": 0.978053,
"date": "2022-10-21"
},
{
"price": 0.991514,
"date": "2022-12-02"
}
]