[
{
 "price": 0.949781,
 "date": "2026-02-18"
},
{
 "price": 0.946947,
 "date": "2026-02-19"
},
{
 "price": 0.9456220000000001,
 "date": "2026-02-20"
},
{
 "price": 0.94465,
 "date": "2026-02-23"
},
{
 "price": 0.944078,
 "date": "2026-02-24"
},
{
 "price": 0.943508,
 "date": "2026-02-25"
},
{
 "price": 0.945921,
 "date": "2026-02-26"
},
{
 "price": 0.9483410000000001,
 "date": "2026-02-27"
},
{
 "price": 0.951115,
 "date": "2026-03-02"
},
{
 "price": 0.940846,
 "date": "2026-03-03"
},
{
 "price": 0.934388,
 "date": "2026-03-04"
},
{
 "price": 0.930178,
 "date": "2026-03-05"
},
{
 "price": 0.932546,
 "date": "2026-03-06"
},
{
 "price": 0.916469,
 "date": "2026-03-09"
},
{
 "price": 0.893507,
 "date": "2026-03-10"
},
{
 "price": 0.923998,
 "date": "2026-03-11"
},
{
 "price": 0.91915,
 "date": "2026-03-12"
},
{
 "price": 0.909387,
 "date": "2026-03-13"
},
{
 "price": 0.897362,
 "date": "2026-03-16"
},
{
 "price": 0.894783,
 "date": "2026-03-17"
},
{
 "price": 0.8998050000000001,
 "date": "2026-03-18"
},
{
 "price": 0.91542,
 "date": "2026-03-19"
},
{
 "price": 0.900862,
 "date": "2026-03-20"
},
{
 "price": 0.909787,
 "date": "2026-03-23"
},
{
 "price": 0.88244,
 "date": "2026-03-24"
},
{
 "price": 0.8948699999999999,
 "date": "2026-03-25"
},
{
 "price": 0.892996,
 "date": "2026-03-26"
},
{
 "price": 0.9035259999999999,
 "date": "2026-03-27"
},
{
 "price": 0.899915,
 "date": "2026-03-30"
},
{
 "price": 0.904949,
 "date": "2026-03-31"
},
{
 "price": 0.9051309999999999,
 "date": "2026-04-01"
},
{
 "price": 0.926494,
 "date": "2026-04-02"
},
{
 "price": 0.920972,
 "date": "2026-04-07"
},
{
 "price": 0.9311619999999999,
 "date": "2026-04-08"
},
{
 "price": 0.945894,
 "date": "2026-04-09"
},
{
 "price": 0.9453360000000001,
 "date": "2026-04-10"
},
{
 "price": 0.949547,
 "date": "2026-04-13"
},
{
 "price": 0.989139,
 "date": "2026-04-14"
},
{
 "price": 0.990869,
 "date": "2026-04-15"
},
{
 "price": 0.99182,
 "date": "2026-04-16"
},
{
 "price": 0.9935550000000001,
 "date": "2026-04-17"
},
{
 "price": 0.994065,
 "date": "2026-04-20"
},
{
 "price": 1.0020959999999999,
 "date": "2026-04-21"
},
{
 "price": 1.00464,
 "date": "2026-04-22"
},
{
 "price": 1.004809,
 "date": "2026-04-23"
},
{
 "price": 0.993966,
 "date": "2026-04-24"
},
{
 "price": 0.99292,
 "date": "2026-04-27"
},
{
 "price": 0.9930910000000001,
 "date": "2026-04-28"
},
{
 "price": 0.99482,
 "date": "2026-04-29"
},
{
 "price": 0.996554,
 "date": "2026-04-30"
},
{
 "price": 0.997235,
 "date": "2026-05-04"
},
{
 "price": 1.003681,
 "date": "2026-05-05"
},
{
 "price": 1.003064,
 "date": "2026-05-06"
},
{
 "price": 1.004808,
 "date": "2026-05-07"
},
{
 "price": 1.016091,
 "date": "2026-05-08"
},
{
 "price": 1.019799,
 "date": "2026-05-11"
},
{
 "price": 1.032098,
 "date": "2026-05-12"
},
{
 "price": 1.021741,
 "date": "2026-05-13"
},
{
 "price": 1.026747,
 "date": "2026-05-14"
},
{
 "price": 1.032595,
 "date": "2026-05-15"
},
{
 "price": 1.041279,
 "date": "2026-05-18"
},
{
 "price": 1.033258,
 "date": "2026-05-19"
},
{
 "price": 1.0375050000000001,
 "date": "2026-05-20"
},
{
 "price": 1.038488,
 "date": "2026-05-21"
},
{
 "price": 1.043583,
 "date": "2026-05-22"
},
{
 "price": 1.04424,
 "date": "2026-05-26"
},
{
 "price": 1.042759,
 "date": "2026-05-27"
},
{
 "price": 1.054508,
 "date": "2026-05-28"
},
{
 "price": 1.055505,
 "date": "2026-05-29"
},
{
 "price": 1.060173,
 "date": "2026-06-01"
},
{
 "price": 1.0628529999999998,
 "date": "2026-06-02"
},
{
 "price": 1.0596590000000001,
 "date": "2026-06-03"
},
{
 "price": 1.057315,
 "date": "2026-06-04"
},
{
 "price": 1.051659,
 "date": "2026-06-05"
},
{
 "price": 1.054637,
 "date": "2026-06-08"
},
{
 "price": 1.046542,
 "date": "2026-06-09"
},
{
 "price": 1.055793,
 "date": "2026-06-10"
},
{
 "price": 1.056787,
 "date": "2026-06-11"
},
{
 "price": 1.0536320000000001,
 "date": "2026-06-12"
},
{
 "price": 1.064953,
 "date": "2026-06-15"
},
{
 "price": 1.0735460000000001,
 "date": "2026-06-16"
},
{
 "price": 1.081369,
 "date": "2026-06-17"
},
{
 "price": 1.088398,
 "date": "2026-06-18"
},
{
 "price": 1.080832,
 "date": "2026-06-19"
},
{
 "price": 1.076203,
 "date": "2026-06-22"
},
{
 "price": 1.077212,
 "date": "2026-06-23"
},
{
 "price": 1.0782209999999999,
 "date": "2026-06-24"
},
{
 "price": 1.084351,
 "date": "2026-06-25"
}
]