[
{
"price": 1.013955,
"date": "2024-09-23"
},
{
"price": 1.001886,
"date": "2024-09-20"
},
{
"price": 1.006821,
"date": "2024-09-19"
},
{
"price": 0.994213,
"date": "2024-09-18"
},
{
"price": 0.996327,
"date": "2024-09-17"
},
{
"price": 0.992094,
"date": "2024-09-16"
},
{
"price": 0.998838,
"date": "2024-09-13"
},
{
"price": 0.997628,
"date": "2024-09-12"
},
{
"price": 0.976612,
"date": "2024-09-11"
},
{
"price": 0.982727,
"date": "2024-09-10"
},
{
"price": 0.97233,
"date": "2024-09-09"
},
{
"price": 0.958586,
"date": "2024-09-06"
},
{
"price": 0.969563,
"date": "2024-09-05"
},
{
"price": 0.981526,
"date": "2024-09-04"
},
{
"price": 0.986097,
"date": "2024-09-03"
},
{
"price": 0.998782,
"date": "2024-09-02"
},
{
"price": 0.962517,
"date": "2024-08-09"
},
{
"price": 0.962517,
"date": "2024-08-09"
},
{
"price": 0.959688,
"date": "2024-08-08"
},
{
"price": 0.962344,
"date": "2024-08-07"
},
{
"price": 0.951309,
"date": "2024-08-06"
},
{
"price": 0.946234,
"date": "2024-08-05"
},
{
"price": 0.972824,
"date": "2024-08-02"
},
{
"price": 1.001505,
"date": "2024-08-01"
},
{
"price": 1.008682,
"date": "2024-07-31"
},
{
"price": 0.988373,
"date": "2024-07-30"
},
{
"price": 0.983257,
"date": "2024-07-29"
},
{
"price": 0.982952,
"date": "2024-07-26"
},
{
"price": 0.986138,
"date": "2024-07-25"
},
{
"price": 0.985635,
"date": "2024-07-24"
},
{
"price": 0.998139,
"date": "2024-07-23"
},
{
"price": 0.990191,
"date": "2024-07-22"
},
{
"price": 0.989106,
"date": "2024-07-19"
},
{
"price": 0.988928,
"date": "2024-07-18"
},
{
"price": 0.998285,
"date": "2024-07-17"
},
{
"price": 1.01211,
"date": "2024-07-16"
},
{
"price": 1.011067,
"date": "2024-07-15"
},
{
"price": 1.01362,
"date": "2024-07-12"
},
{
"price": 1.01271,
"date": "2024-07-11"
},
{
"price": 1.015986,
"date": "2024-07-10"
},
{
"price": 1.018723,
"date": "2024-07-09"
},
{
"price": 1.009521,
"date": "2024-07-08"
},
{
"price": 1.004725,
"date": "2024-07-05"
},
{
"price": 1.005823,
"date": "2024-07-04"
},
{
"price": 1.011711,
"date": "2024-07-03"
},
{
"price": 1.009372,
"date": "2024-07-02"
},
{
"price": 1.0,
"date": "2024-07-01"
},
{
"price": 0.960157,
"date": "2024-08-12"
},
{
"price": 0.970406,
"date": "2024-08-13"
},
{
"price": 0.971127,
"date": "2024-08-14"
},
{
"price": 0.988135,
"date": "2024-08-15"
},
{
"price": 0.995096,
"date": "2024-08-16"
},
{
"price": 0.987945,
"date": "2024-08-21"
},
{
"price": 0.986104,
"date": "2024-08-22"
},
{
"price": 0.993243,
"date": "2024-08-23"
},
{
"price": 0.990744,
"date": "2024-08-26"
},
{
"price": 0.988149,
"date": "2024-08-27"
},
{
"price": 0.984424,
"date": "2024-08-28"
},
{
"price": 0.993942,
"date": "2024-08-29"
},
{
"price": 0.991172,
"date": "2024-08-30"
},
{
 "price": 1.011226,
 "date": "2024-09-24"
},
{
 "price": 1.008734,
 "date": "2024-09-25"
},
{
 "price": 1.01554,
 "date": "2024-09-26"
},
{
 "price": 1.020358,
 "date": "2024-09-27"
},
{
 "price": 1.014913,
 "date": "2024-09-30"
},
{
 "price": 1.017337,
 "date": "2024-10-01"
},
{
 "price": 1.026148,
 "date": "2024-10-02"
},
{
 "price": 1.029615,
 "date": "2024-10-03"
},
{
 "price": 1.036795,
 "date": "2024-10-04"
},
{
 "price": 1.044662,
 "date": "2024-10-07"
},
{
 "price": 1.042285,
 "date": "2024-10-08"
},
{
 "price": 1.049076,
 "date": "2024-10-09"
},
{
 "price": 1.051845,
 "date": "2024-10-10"
},
{
 "price": 1.057951,
 "date": "2024-10-11"
},
{
 "price": 1.066482,
 "date": "2024-10-14"
},
{
 "price": 1.066019,
 "date": "2024-10-15"
},
{
 "price": 1.067099,
 "date": "2024-10-16"
},
{
 "price": 1.079075,
 "date": "2024-10-17"
},
{
 "price": 1.075686,
 "date": "2024-10-18"
},
{
 "price": 1.072845,
 "date": "2024-10-21"
},
{
 "price": 1.075112,
 "date": "2024-10-22"
},
{
 "price": 1.076006,
 "date": "2024-10-24"
},
{
 "price": 1.083355,
 "date": "2024-10-25"
},
{
 "price": 1.084295,
 "date": "2024-10-28"
},
{
 "price": 1.084767,
 "date": "2024-10-29"
},
{
 "price": 1.088679,
 "date": "2024-10-30"
},
{
 "price": 1.070145,
 "date": "2024-10-31"
},
{
 "price": 1.065057,
 "date": "2024-11-04"
},
{
 "price": 1.078924,
 "date": "2024-11-05"
},
{
 "price": 1.119165,
 "date": "2024-11-06"
},
{
 "price": 1.122888,
 "date": "2024-11-07"
},
{
 "price": 1.122532,
 "date": "2024-11-08"
},
{
 "price": 1.141768,
 "date": "2024-11-11"
},
{
 "price": 1.147106,
 "date": "2024-11-12"
},
{
 "price": 1.144578,
 "date": "2024-11-13"
},
{
 "price": 1.146797,
 "date": "2024-11-14"
},
{
 "price": 1.12142,
 "date": "2024-11-15"
},
{
 "price": 1.133883,
 "date": "2024-11-18"
},
{
 "price": 1.130687,
 "date": "2024-11-19"
},
{
 "price": 1.133829,
 "date": "2024-11-20"
},
{
 "price": 1.152724,
 "date": "2024-11-21"
},
{
 "price": 1.168462,
 "date": "2024-11-22"
},
{
 "price": 1.166975,
 "date": "2024-11-25"
},
{
 "price": 1.167149,
 "date": "2024-11-26"
},
{
 "price": 1.16254,
 "date": "2024-11-27"
},
{
 "price": 1.172634,
 "date": "2024-11-28"
},
{
 "price": 1.16974,
 "date": "2024-11-29"
},
{
 "price": 1.177453,
 "date": "2024-12-02"
},
{
 "price": 1.176349,
 "date": "2024-12-03"
},
{
 "price": 1.183731,
 "date": "2024-12-04"
},
{
 "price": 1.17722,
 "date": "2024-12-05"
},
{
 "price": 1.176537,
 "date": "2024-12-06"
},
{
 "price": 1.164454,
 "date": "2024-12-09"
},
{
 "price": 1.165076,
 "date": "2024-12-10"
},
{
 "price": 1.178453,
 "date": "2024-12-11"
},
{
 "price": 1.171789,
 "date": "2024-12-12"
},
{
 "price": 1.17033,
 "date": "2024-12-13"
},
{
 "price": 1.171503,
 "date": "2024-12-16"
},
{
 "price": 1.170108,
 "date": "2024-12-17"
},
{
 "price": 1.158097,
 "date": "2024-12-18"
},
{
 "price": 1.161126,
 "date": "2024-12-19"
},
{
 "price": 1.171079,
 "date": "2024-12-20"
},
{
 "price": 1.169291,
 "date": "2024-12-23"
},
{
 "price": 1.150269,
 "date": "2024-12-30"
},
{
 "price": 1.1496,
 "date": "2024-12-31"
},
{
 "price": 1.15557,
 "date": "2025-01-02"
},
{
 "price": 1.177836,
 "date": "2025-01-03"
},
{
 "price": 1.183404,
 "date": "2025-01-06"
},
{
 "price": 1.164556,
 "date": "2025-01-07"
},
{
 "price": 1.170148,
 "date": "2025-01-08"
},
{
 "price": 1.16754,
 "date": "2025-01-09"
},
{
 "price": 1.150482,
 "date": "2025-01-10"
},
{
 "price": 1.160926,
 "date": "2025-01-13"
},
{
 "price": 1.154617,
 "date": "2025-01-14"
},
{
 "price": 1.165135,
 "date": "2025-01-15"
},
{
 "price": 1.173247,
 "date": "2025-01-16"
},
{
 "price": 1.188739,
 "date": "2025-01-17"
},
{
 "price": 1.18758,
 "date": "2025-01-20"
},
{
 "price": 1.186019,
 "date": "2025-01-21"
},
{
 "price": 1.185357,
 "date": "2025-01-22"
},
{
 "price": 1.187019,
 "date": "2025-01-23"
},
{
 "price": 1.176161,
 "date": "2025-01-24"
},
{
 "price": 1.148066,
 "date": "2025-01-27"
},
{
 "price": 1.165475,
 "date": "2025-01-28"
},
{
 "price": 1.165961,
 "date": "2025-01-29"
},
{
 "price": 1.167294,
 "date": "2025-01-30"
},
{
 "price": 1.177774,
 "date": "2025-01-31"
},
{
 "price": 1.181596,
 "date": "2025-02-03"
},
{
 "price": 1.173223,
 "date": "2025-02-04"
},
{
 "price": 1.160382,
 "date": "2025-02-05"
},
{
 "price": 1.174719,
 "date": "2025-02-06"
},
{
 "price": 1.157383,
 "date": "2025-02-07"
},
{
 "price": 1.170568,
 "date": "2025-02-10"
},
{
 "price": 1.166326,
 "date": "2025-02-11"
},
{
 "price": 1.15083,
 "date": "2025-02-12"
},
{
 "price": 1.154318,
 "date": "2025-02-13"
},
{
 "price": 1.151892,
 "date": "2025-02-14"
},
{
 "price": 1.157689,
 "date": "2025-02-17"
},
{
 "price": 1.155978,
 "date": "2025-02-18"
},
{
 "price": 1.160845,
 "date": "2025-02-19"
},
{
 "price": 1.155372,
 "date": "2025-02-20"
},
{
 "price": 1.148469,
 "date": "2025-02-21"
},
{
 "price": 1.130391,
 "date": "2025-02-24"
},
{
 "price": 1.109974,
 "date": "2025-02-25"
},
{
 "price": 1.116634,
 "date": "2025-02-26"
},
{
 "price": 1.105119,
 "date": "2025-02-27"
},
{
 "price": 1.11295,
 "date": "2025-02-28"
},
{
 "price": 1.112855,
 "date": "2025-03-03"
},
{
 "price": 1.067774,
 "date": "2025-03-04"
},
{
 "price": 1.052427,
 "date": "2025-03-05"
},
{
 "price": 1.046258,
 "date": "2025-03-06"
},
{
 "price": 1.024451,
 "date": "2025-03-07"
},
{
 "price": 1.011281,
 "date": "2025-03-10"
},
{
 "price": 1.000768,
 "date": "2025-03-11"
},
{
 "price": 1.008189,
 "date": "2025-03-12"
},
{
 "price": 0.992925,
 "date": "2025-03-13"
},
{
 "price": 1.011889,
 "date": "2025-03-14"
},
{
 "price": 1.012526,
 "date": "2025-03-17"
},
{
 "price": 0.997791,
 "date": "2025-03-18"
},
{
 "price": 1.013447,
 "date": "2025-03-19"
},
{
 "price": 1.018429,
 "date": "2025-03-20"
},
{
 "price": 1.018233,
 "date": "2025-03-21"
},
{
 "price": 1.033977,
 "date": "2025-03-24"
},
{
 "price": 1.041744,
 "date": "2025-03-25"
},
{
 "price": 1.036749,
 "date": "2025-03-26"
},
{
 "price": 1.035616,
 "date": "2025-03-27"
},
{
 "price": 1.022598,
 "date": "2025-03-28"
},
{
 "price": 1.012533,
 "date": "2025-03-31"
},
{
 "price": 1.025764,
 "date": "2025-04-01"
},
{
 "price": 1.027743,
 "date": "2025-04-02"
},
{
 "price": 0.972845,
 "date": "2025-04-03"
},
{
 "price": 0.940301,
 "date": "2025-04-04"
},
{
 "price": 0.925182,
 "date": "2025-04-07"
},
{
 "price": 0.947814,
 "date": "2025-04-08"
},
{
 "price": 0.942765,
 "date": "2025-04-09"
},
{
 "price": 0.955826,
 "date": "2025-04-10"
},
{
 "price": 0.93642,
 "date": "2025-04-11"
},
{
 "price": 0.962224,
 "date": "2025-04-14"
},
{
 "price": 0.965505,
 "date": "2025-04-15"
},
{
 "price": 0.948597,
 "date": "2025-04-16"
},
{
 "price": 0.938127,
 "date": "2025-04-17"
},
{
 "price": 0.930013,
 "date": "2025-04-22"
},
{
 "price": 0.953954,
 "date": "2025-04-23"
},
{
 "price": 0.96353,
 "date": "2025-04-24"
},
{
 "price": 0.970909,
 "date": "2025-04-25"
},
{
 "price": 0.968999,
 "date": "2025-04-28"
},
{
 "price": 0.968794,
 "date": "2025-04-29"
},
{
 "price": 0.968727,
 "date": "2025-04-30"
},
{
 "price": 0.993817,
 "date": "2025-05-05"
},
{
 "price": 0.990282,
 "date": "2025-05-06"
},
{
 "price": 0.983966,
 "date": "2025-05-07"
},
{
 "price": 1.001954,
 "date": "2025-05-08"
},
{
 "price": 1.000833,
 "date": "2025-05-09"
},
{
 "price": 1.037951,
 "date": "2025-05-12"
},
{
 "price": 1.053205,
 "date": "2025-05-13"
},
{
 "price": 1.038633,
 "date": "2025-05-14"
},
{
 "price": 1.041133,
 "date": "2025-05-15"
},
{
 "price": 1.046915,
 "date": "2025-05-16"
},
{
 "price": 1.042931,
 "date": "2025-05-19"
},
{
 "price": 1.042013,
 "date": "2025-05-20"
},
{
 "price": 1.030541,
 "date": "2025-05-21"
},
{
 "price": 1.023315,
 "date": "2025-05-22"
},
{
 "price": 1.01236,
 "date": "2025-05-23"
},
{
 "price": 1.012146,
 "date": "2025-05-26"
},
{
 "price": 1.032625,
 "date": "2025-05-27"
},
{
 "price": 1.030164,
 "date": "2025-05-28"
},
{
 "price": 1.039077,
 "date": "2025-05-29"
},
{
 "price": 1.032139,
 "date": "2025-05-30"
},
{
 "price": 1.021811,
 "date": "2025-06-02"
},
{
 "price": 1.033599,
 "date": "2025-06-03"
},
{
 "price": 1.037355,
 "date": "2025-06-04"
},
{
 "price": 1.035816,
 "date": "2025-06-05"
},
{
 "price": 1.038264,
 "date": "2025-06-06"
},
{
 "price": 1.037625,
 "date": "2025-06-10"
},
{
 "price": 1.036909,
 "date": "2025-06-11"
},
{
 "price": 1.026174,
 "date": "2025-06-12"
},
{
 "price": 1.025719,
 "date": "2025-06-13"
},
{
 "price": 1.024645,
 "date": "2025-06-16"
},
{
 "price": 1.024955,
 "date": "2025-06-17"
},
{
 "price": 1.031132,
 "date": "2025-06-18"
},
{
 "price": 1.020893,
 "date": "2025-06-19"
},
{
 "price": 1.022359,
 "date": "2025-06-20"
},
{
 "price": 1.031216,
 "date": "2025-06-23"
},
{
 "price": 1.0292,
 "date": "2025-06-24"
},
{
 "price": 1.026497,
 "date": "2025-06-25"
},
{
 "price": 1.020759,
 "date": "2025-06-26"
},
{
 "price": 1.02755,
 "date": "2025-06-27"
},
{
 "price": 1.028315,
 "date": "2025-06-30"
},
{
 "price": 1.021859,
 "date": "2025-07-01"
},
{
 "price": 1.027221,
 "date": "2025-07-02"
},
{
 "price": 1.037354,
 "date": "2025-07-03"
},
{
 "price": 1.031929,
 "date": "2025-07-04"
},
{
 "price": 1.037108,
 "date": "2025-07-07"
},
{
 "price": 1.032162,
 "date": "2025-07-08"
},
{
 "price": 1.041194,
 "date": "2025-07-09"
},
{
 "price": 1.040234,
 "date": "2025-07-10"
},
{
 "price": 1.042196,
 "date": "2025-07-11"
},
{
 "price": 1.044323,
 "date": "2025-07-14"
},
{
 "price": 1.044454,
 "date": "2025-07-15"
},
{
 "price": 1.043238,
 "date": "2025-07-16"
},
{
 "price": 1.054401,
 "date": "2025-07-17"
},
{
 "price": 1.051282,
 "date": "2025-07-18"
},
{
 "price": 1.055748,
 "date": "2025-07-21"
},
{
 "price": 1.045851,
 "date": "2025-07-22"
},
{
 "price": 1.047786,
 "date": "2025-07-23"
},
{
 "price": 1.049338,
 "date": "2025-07-24"
},
{
 "price": 1.046912,
 "date": "2025-07-25"
},
{
 "price": 1.056711,
 "date": "2025-07-28"
},
{
 "price": 1.069666,
 "date": "2025-07-29"
},
{
 "price": 1.069438,
 "date": "2025-07-30"
},
{
 "price": 1.081306,
 "date": "2025-07-31"
},
{
 "price": 1.061925,
 "date": "2025-08-01"
},
{
 "price": 1.056857,
 "date": "2025-08-04"
},
{
 "price": 1.059709,
 "date": "2025-08-05"
},
{
 "price": 1.059677,
 "date": "2025-08-06"
},
{
 "price": 1.047463,
 "date": "2025-08-07"
},
{
 "price": 1.054383,
 "date": "2025-08-08"
},
{
 "price": 1.051852,
 "date": "2025-08-11"
},
{
 "price": 1.065321,
 "date": "2025-08-12"
},
{
 "price": 1.059458,
 "date": "2025-08-13"
},
{
 "price": 1.064274,
 "date": "2025-08-14"
},
{
 "price": 1.061965,
 "date": "2025-08-15"
},
{
 "price": 1.061113,
 "date": "2025-08-18"
},
{
 "price": 1.053318,
 "date": "2025-08-19"
},
{
 "price": 1.054906,
 "date": "2025-08-21"
},
{
 "price": 1.074312,
 "date": "2025-08-22"
},
{
 "price": 1.065116,
 "date": "2025-08-25"
},
{
 "price": 1.070658,
 "date": "2025-08-26"
},
{
 "price": 1.07503,
 "date": "2025-08-27"
},
{
 "price": 1.0739,
 "date": "2025-08-28"
},
{
 "price": 1.065782,
 "date": "2025-08-29"
},
{
 "price": 1.058308,
 "date": "2025-09-01"
},
{
 "price": 1.056692,
 "date": "2025-09-02"
},
{
 "price": 1.058461,
 "date": "2025-09-03"
},
{
 "price": 1.062963,
 "date": "2025-09-04"
},
{
 "price": 1.057863,
 "date": "2025-09-05"
},
{
 "price": 1.058063,
 "date": "2025-09-08"
},
{
 "price": 1.057696,
 "date": "2025-09-09"
},
{
 "price": 1.067654,
 "date": "2025-09-10"
},
{
 "price": 1.074865,
 "date": "2025-09-11"
},
{
 "price": 1.068612,
 "date": "2025-09-12"
},
{
 "price": 1.066501,
 "date": "2025-09-15"
},
{
 "price": 1.059725,
 "date": "2025-09-16"
},
{
 "price": 1.053921,
 "date": "2025-09-17"
},
{
 "price": 1.060206,
 "date": "2025-09-18"
},
{
 "price": 1.069592,
 "date": "2025-09-19"
},
{
 "price": 1.074374,
 "date": "2025-09-22"
},
{
 "price": 1.069934,
 "date": "2025-09-23"
},
{
 "price": 1.069952,
 "date": "2025-09-24"
},
{
 "price": 1.067292,
 "date": "2025-09-25"
},
{
 "price": 1.078689,
 "date": "2025-09-26"
},
{
 "price": 1.078135,
 "date": "2025-09-29"
},
{
 "price": 1.076758,
 "date": "2025-09-30"
},
{
 "price": 1.078081,
 "date": "2025-10-01"
},
{
 "price": 1.080052,
 "date": "2025-10-02"
},
{
 "price": 1.085297,
 "date": "2025-10-03"
},
{
 "price": 1.090761,
 "date": "2025-10-06"
},
{
 "price": 1.096993,
 "date": "2025-10-07"
},
{
 "price": 1.109055,
 "date": "2025-10-08"
},
{
 "price": 1.105505,
 "date": "2025-10-09"
},
{
 "price": 1.086444,
 "date": "2025-10-10"
},
{
 "price": 1.096463,
 "date": "2025-10-13"
},
{
 "price": 1.097659,
 "date": "2025-10-14"
},
{
 "price": 1.093724,
 "date": "2025-10-15"
},
{
 "price": 1.087489,
 "date": "2025-10-16"
},
{
 "price": 1.078487,
 "date": "2025-10-17"
},
{
 "price": 1.09642,
 "date": "2025-10-20"
},
{
 "price": 1.100839,
 "date": "2025-10-21"
},
{
 "price": 1.095389,
 "date": "2025-10-22"
},
{
 "price": 1.117442,
 "date": "2025-10-27"
},
{
 "price": 1.115997,
 "date": "2025-10-28"
},
{
 "price": 1.119048,
 "date": "2025-10-29"
},
{
 "price": 1.114776,
 "date": "2025-10-30"
},
{
 "price": 1.116317,
 "date": "2025-10-31"
}
]