[
{
"price": 1.736132,
"date": "2024-09-23"
},
{
"price": 1.7302,
"date": "2024-09-20"
},
{
"price": 1.769607,
"date": "2024-09-19"
},
{
"price": 1.763745,
"date": "2024-09-18"
},
{
"price": 1.765734,
"date": "2024-09-17"
},
{
"price": 1.736327,
"date": "2024-09-16"
},
{
"price": 1.757555,
"date": "2024-09-13"
},
{
"price": 1.72843,
"date": "2024-09-12"
},
{
"price": 1.706051,
"date": "2024-09-11"
},
{
"price": 1.743168,
"date": "2024-09-10"
},
{
"price": 1.750659,
"date": "2024-09-09"
},
{
"price": 1.738647,
"date": "2024-09-06"
},
{
"price": 1.778054,
"date": "2024-09-05"
},
{
"price": 1.80065,
"date": "2024-09-04"
},
{
"price": 1.805518,
"date": "2024-09-03"
},
{
"price": 1.834945,
"date": "2024-09-02"
},
{
"price": 1.68708,
"date": "2024-08-09"
},
{
"price": 1.68708,
"date": "2024-08-09"
},
{
"price": 1.698634,
"date": "2024-08-08"
},
{
"price": 1.68811,
"date": "2024-08-07"
},
{
"price": 1.676574,
"date": "2024-08-06"
},
{
"price": 1.706147,
"date": "2024-08-05"
},
{
"price": 1.761099,
"date": "2024-08-02"
},
{
"price": 1.782409,
"date": "2024-08-01"
},
{
"price": 1.815839,
"date": "2024-07-31"
},
{
"price": 1.789031,
"date": "2024-07-30"
},
{
"price": 1.799069,
"date": "2024-07-29"
},
{
"price": 1.795841,
"date": "2024-07-26"
},
{
"price": 1.79971,
"date": "2024-07-25"
},
{
"price": 1.809227,
"date": "2024-07-24"
},
{
"price": 1.811557,
"date": "2024-07-23"
},
{
"price": 1.838581,
"date": "2024-07-22"
},
{
"price": 1.832997,
"date": "2024-07-19"
},
{
"price": 1.838594,
"date": "2024-07-18"
},
{
"price": 1.813315,
"date": "2024-07-17"
},
{
"price": 1.852016,
"date": "2024-07-16"
},
{
"price": 1.914398,
"date": "2024-07-15"
},
{
"price": 1.918004,
"date": "2024-07-12"
},
{
"price": 1.907555,
"date": "2024-07-11"
},
{
"price": 1.892739,
"date": "2024-07-10"
},
{
"price": 1.917248,
"date": "2024-07-09"
},
{
"price": 1.898013,
"date": "2024-07-08"
},
{
"price": 1.875693,
"date": "2024-07-05"
},
{
"price": 1.898492,
"date": "2024-07-04"
},
{
"price": 1.89627,
"date": "2024-07-03"
},
{
"price": 1.88183,
"date": "2024-07-02"
},
{
"price": 1.901313,
"date": "2024-07-01"
},
{
"price": 1.907399,
"date": "2024-06-28"
},
{
"price": 1.904744,
"date": "2024-06-27"
},
{
"price": 1.897984,
"date": "2024-06-26"
},
{
"price": 1.902732,
"date": "2024-06-25"
},
{
"price": 1.890355,
"date": "2024-06-24"
},
{
"price": 1.863135,
"date": "2024-06-21"
},
{
"price": 1.864519,
"date": "2024-06-20"
},
{
"price": 1.850477,
"date": "2024-06-19"
},
{
"price": 1.822012,
"date": "2024-06-18"
},
{
"price": 1.823549,
"date": "2024-06-17"
},
{
"price": 1.798935,
"date": "2024-06-14"
},
{
"price": 1.792797,
"date": "2024-06-13"
},
{
"price": 1.820319,
"date": "2024-06-12"
},
{
"price": 1.789222,
"date": "2024-06-11"
},
{
"price": 1.810233,
"date": "2024-06-10"
},
{
"price": 1.807698,
"date": "2024-06-07"
},
{
"price": 1.838552,
"date": "2024-06-06"
},
{
"price": 1.821537,
"date": "2024-06-05"
},
{
"price": 1.817578,
"date": "2024-06-04"
},
{
"price": 1.859974,
"date": "2024-06-03"
},
{
"price": 1.854281,
"date": "2024-05-31"
},
{
"price": 1.822867,
"date": "2024-05-29"
},
{
"price": 1.847437,
"date": "2024-05-28"
},
{
"price": 1.86491,
"date": "2024-05-27"
},
{
"price": 1.866692,
"date": "2024-05-24"
},
{
"price": 1.874863,
"date": "2024-05-23"
},
{
"price": 1.878665,
"date": "2024-05-22"
},
{
"price": 1.88561,
"date": "2024-05-21"
},
{
"price": 1.897536,
"date": "2024-05-17"
},
{
"price": 1.884793,
"date": "2024-05-16"
},
{
"price": 1.882475,
"date": "2024-05-15"
},
{
"price": 1.873438,
"date": "2024-05-14"
},
{
"price": 1.862183,
"date": "2024-05-13"
},
{
"price": 1.8522,
"date": "2024-05-10"
},
{
"price": 1.882954,
"date": "2024-05-09"
},
{
"price": 1.866219,
"date": "2024-05-08"
},
{
"price": 1.860404,
"date": "2024-05-07"
},
{
"price": 1.864386,
"date": "2024-05-06"
},
{
"price": 1.809674,
"date": "2024-05-02"
},
{
"price": 1.824813,
"date": "2024-04-30"
},
{
"price": 1.850383,
"date": "2024-04-29"
},
{
"price": 1.835159,
"date": "2024-04-26"
},
{
"price": 1.813543,
"date": "2024-04-25"
},
{
"price": 1.835203,
"date": "2024-04-24"
},
{
"price": 1.848987,
"date": "2024-04-23"
},
{
"price": 1.854084,
"date": "2024-04-22"
},
{
"price": 1.812409,
"date": "2024-04-19"
},
{
"price": 1.805603,
"date": "2024-04-18"
},
{
"price": 1.780229,
"date": "2024-04-17"
},
{
"price": 1.766337,
"date": "2024-04-16"
},
{
"price": 1.816426,
"date": "2024-04-15"
},
{
"price": 1.812118,
"date": "2024-04-12"
},
{
"price": 1.823802,
"date": "2024-04-11"
},
{
"price": 1.850167,
"date": "2024-04-10"
},
{
"price": 1.822147,
"date": "2024-04-09"
},
{
"price": 1.845748,
"date": "2024-04-08"
},
{
"price": 1.820597,
"date": "2024-04-05"
},
{
"price": 1.825199,
"date": "2024-04-04"
},
{
"price": 1.813864,
"date": "2024-04-03"
},
{
"price": 1.82251,
"date": "2024-04-02"
},
{
"price": 1.817859,
"date": "2024-03-28"
},
{
"price": 1.789576,
"date": "2024-03-27"
},
{
"price": 1.790934,
"date": "2024-03-26"
},
{
"price": 1.75979,
"date": "2024-03-25"
},
{
"price": 1.783572,
"date": "2024-03-22"
},
{
"price": 1.793659,
"date": "2024-03-21"
},
{
"price": 1.741094,
"date": "2024-03-20"
},
{
"price": 1.739497,
"date": "2024-03-19"
},
{
"price": 1.747157,
"date": "2024-03-18"
},
{
"price": 1.803801,
"date": "2024-03-14"
},
{
"price": 1.816824,
"date": "2024-03-13"
},
{
"price": 1.825321,
"date": "2024-03-12"
},
{
"price": 1.777152,
"date": "2024-03-11"
},
{
"price": 1.760167,
"date": "2024-03-08"
},
{
"price": 1.749705,
"date": "2024-03-07"
},
{
"price": 1.765414,
"date": "2024-03-06"
},
{
"price": 1.768453,
"date": "2024-03-05"
},
{
"price": 1.781952,
"date": "2024-03-04"
},
{
"price": 1.800178,
"date": "2024-03-01"
},
{
"price": 1.795525,
"date": "2024-02-29"
},
{
"price": 1.784367,
"date": "2024-02-28"
},
{
"price": 1.813065,
"date": "2024-02-27"
},
{
"price": 1.816071,
"date": "2024-02-26"
},
{
"price": 1.812223,
"date": "2024-02-23"
},
{
"price": 1.791254,
"date": "2024-02-22"
},
{
"price": 1.770747,
"date": "2024-02-21"
},
{
"price": 1.784197,
"date": "2024-02-20"
},
{
"price": 1.753256,
"date": "2024-02-19"
},
{
"price": 1.740139,
"date": "2024-02-16"
},
{
"price": 1.720494,
"date": "2024-02-15"
},
{
"price": 1.719529,
"date": "2024-02-14"
},
{
"price": 1.690217,
"date": "2024-02-13"
},
{
"price": 1.722929,
"date": "2024-02-12"
},
{
"price": 1.707363,
"date": "2024-02-09"
},
{
"price": 1.700617,
"date": "2024-02-08"
},
{
"price": 1.715138,
"date": "2024-02-07"
},
{
"price": 1.702125,
"date": "2024-02-06"
},
{
"price": 1.697467,
"date": "2024-02-05"
},
{
"price": 1.712854,
"date": "2024-02-02"
},
{
"price": 1.686021,
"date": "2024-02-01"
},
{
"price": 1.659973,
"date": "2024-01-31"
},
{
"price": 1.641235,
"date": "2024-01-30"
},
{
"price": 1.620937,
"date": "2024-01-29"
},
{
"price": 1.6111,
"date": "2024-01-26"
},
{
"price": 1.596918,
"date": "2024-01-25"
},
{
"price": 1.602693,
"date": "2024-01-24"
},
{
"price": 1.585836,
"date": "2024-01-23"
},
{
"price": 1.593411,
"date": "2024-01-22"
},
{
"price": 1.584418,
"date": "2024-01-19"
},
{
"price": 1.567217,
"date": "2024-01-18"
},
{
"price": 1.548817,
"date": "2024-01-17"
},
{
"price": 1.572847,
"date": "2024-01-16"
},
{
"price": 1.585482,
"date": "2024-01-15"
},
{
"price": 1.611623,
"date": "2024-01-12"
},
{
"price": 1.608184,
"date": "2024-01-11"
},
{
"price": 1.622645,
"date": "2024-01-10"
},
{
"price": 1.636431,
"date": "2024-01-09"
},
{
"price": 1.61892,
"date": "2024-01-08"
},
{
"price": 1.617553,
"date": "2024-01-05"
},
{
"price": 1.626925,
"date": "2024-01-04"
},
{
"price": 1.637168,
"date": "2024-01-03"
},
{
"price": 1.656936,
"date": "2024-01-02"
},
{
"price": 1.686151,
"date": "2023-12-29"
},
{
"price": 1.693638,
"date": "2023-12-28"
},
{
"price": 1.707308,
"date": "2023-12-27"
},
{
"price": 1.692068,
"date": "2023-12-22"
},
{
"price": 1.692747,
"date": "2023-12-21"
},
{
"price": 1.701052,
"date": "2023-12-20"
},
{
"price": 1.698379,
"date": "2023-12-19"
},
{
"price": 1.69013,
"date": "2023-12-18"
},
{
"price": 1.67024,
"date": "2023-12-15"
},
{
"price": 1.665584,
"date": "2023-12-14"
},
{
"price": 1.655927,
"date": "2023-12-13"
},
{
"price": 1.652252,
"date": "2023-12-12"
},
{
"price": 1.660185,
"date": "2023-12-11"
},
{
"price": 1.664827,
"date": "2023-12-08"
},
{
"price": 1.646314,
"date": "2023-12-07"
},
{
"price": 1.654776,
"date": "2023-12-06"
},
{
"price": 1.649543,
"date": "2023-12-05"
},
{
"price": 1.634207,
"date": "2023-12-04"
},
{
"price": 1.632381,
"date": "2023-12-01"
},
{
"price": 1.585632,
"date": "2023-11-30"
},
{
"price": 1.589375,
"date": "2023-11-29"
},
{
"price": 1.601481,
"date": "2023-11-28"
},
{
"price": 1.57944,
"date": "2023-11-27"
},
{
"price": 1.585659,
"date": "2023-11-24"
},
{
"price": 1.584798,
"date": "2023-11-23"
},
{
"price": 1.593393,
"date": "2023-11-22"
},
{
"price": 1.593656,
"date": "2023-11-21"
},
{
"price": 1.593923,
"date": "2023-11-20"
},
{
"price": 1.569238,
"date": "2023-11-17"
},
{
"price": 1.55794,
"date": "2023-11-16"
},
{
"price": 1.558979,
"date": "2023-11-15"
},
{
"price": 1.560752,
"date": "2023-11-14"
},
{
"price": 1.489829,
"date": "2023-11-13"
},
{
"price": 1.500728,
"date": "2023-11-10"
},
{
"price": 1.52011,
"date": "2023-11-09"
},
{
"price": 1.493369,
"date": "2023-11-08"
},
{
"price": 1.514047,
"date": "2023-11-07"
},
{
"price": 1.525675,
"date": "2023-11-06"
},
{
"price": 1.525922,
"date": "2023-11-03"
},
{
"price": 1.524095,
"date": "2023-11-02"
},
{
"price": 1.522292,
"date": "2023-10-31"
},
{
"price": 1.510451,
"date": "2023-10-30"
},
{
"price": 1.494741,
"date": "2023-10-27"
},
{
"price": 1.504983,
"date": "2023-10-26"
},
{
"price": 1.494406,
"date": "2023-10-25"
},
{
"price": 1.463206,
"date": "2023-10-24"
},
{
"price": 1.452939,
"date": "2023-10-20"
},
{
"price": 1.475778,
"date": "2023-10-19"
},
{
"price": 1.501462,
"date": "2023-10-18"
},
{
"price": 1.529192,
"date": "2023-10-17"
},
{
"price": 1.501278,
"date": "2023-10-16"
},
{
"price": 1.431324,
"date": "2023-10-13"
},
{
"price": 1.428071,
"date": "2023-10-12"
},
{
"price": 1.435254,
"date": "2023-10-11"
},
{
"price": 1.422629,
"date": "2023-10-10"
},
{
"price": 1.392692,
"date": "2023-10-09"
},
{
"price": 1.377745,
"date": "2023-10-06"
},
{
"price": 1.376705,
"date": "2023-10-05"
},
{
"price": 1.381635,
"date": "2023-10-04"
},
{
"price": 1.378855,
"date": "2023-10-03"
},
{
"price": 1.384311,
"date": "2023-10-02"
},
{
"price": 1.406575,
"date": "2023-09-29"
},
{
"price": 1.393109,
"date": "2023-09-28"
},
{
"price": 1.389781,
"date": "2023-09-27"
},
{
"price": 1.391009,
"date": "2023-09-26"
},
{
"price": 1.393253,
"date": "2023-09-25"
},
{
"price": 1.391065,
"date": "2023-09-22"
},
{
"price": 1.388024,
"date": "2023-09-21"
},
{
"price": 1.399254,
"date": "2023-09-20"
},
{
"price": 1.390628,
"date": "2023-09-19"
},
{
"price": 1.390834,
"date": "2023-09-18"
},
{
"price": 1.406427,
"date": "2023-09-15"
},
{
"price": 1.406916,
"date": "2023-09-14"
},
{
"price": 1.3949,
"date": "2023-09-13"
},
{
"price": 1.391954,
"date": "2023-09-12"
},
{
"price": 1.385265,
"date": "2023-09-11"
},
{
"price": 1.386326,
"date": "2023-09-08"
},
{
"price": 1.398034,
"date": "2023-09-07"
},
{
"price": 1.40701,
"date": "2023-09-06"
},
{
"price": 1.412024,
"date": "2023-09-05"
},
{
"price": 1.416459,
"date": "2023-09-04"
},
{
"price": 1.42649,
"date": "2023-09-01"
},
{
"price": 1.411935,
"date": "2023-08-31"
},
{
"price": 1.424047,
"date": "2023-08-30"
},
{
"price": 1.427086,
"date": "2023-08-29"
},
{
"price": 1.423865,
"date": "2023-08-28"
},
{
"price": 1.408608,
"date": "2023-08-25"
},
{
"price": 1.413205,
"date": "2023-08-24"
},
{
"price": 1.408501,
"date": "2023-08-23"
},
{
"price": 1.409725,
"date": "2023-08-22"
},
{
"price": 1.40736,
"date": "2023-08-21"
},
{
"price": 1.405569,
"date": "2023-08-18"
},
{
"price": 1.416925,
"date": "2023-08-17"
},
{
"price": 1.425177,
"date": "2023-08-16"
},
{
"price": 1.437063,
"date": "2023-08-14"
},
{
"price": 1.448007,
"date": "2023-08-11"
},
{
"price": 1.459081,
"date": "2023-08-10"
},
{
"price": 1.448367,
"date": "2023-08-09"
},
{
"price": 1.45767,
"date": "2023-08-08"
},
{
"price": 1.476097,
"date": "2023-08-07"
},
{
"price": 1.474711,
"date": "2023-08-04"
},
{
"price": 1.471103,
"date": "2023-08-03"
},
{
"price": 1.466527,
"date": "2023-08-02"
},
{
"price": 1.488156,
"date": "2023-08-01"
},
{
"price": 1.473219,
"date": "2023-07-31"
},
{
"price": 1.464079,
"date": "2023-07-28"
},
{
"price": 1.449607,
"date": "2023-07-27"
},
{
"price": 1.443363,
"date": "2023-07-26"
},
{
"price": 1.436787,
"date": "2023-07-25"
},
{
"price": 1.429262,
"date": "2023-07-24"
},
{
"price": 1.43057,
"date": "2023-07-21"
},
{
"price": 1.425349,
"date": "2023-07-20"
},
{
"price": 1.410335,
"date": "2023-07-19"
},
{
"price": 1.403388,
"date": "2023-07-18"
},
{
"price": 1.388061,
"date": "2023-07-17"
},
{
"price": 1.393558,
"date": "2023-07-14"
},
{
"price": 1.39664,
"date": "2023-07-13"
},
{
"price": 1.389951,
"date": "2023-07-12"
},
{
"price": 1.375912,
"date": "2023-07-11"
},
{
"price": 1.376918,
"date": "2023-07-10"
},
{
"price": 1.382997,
"date": "2023-07-07"
},
{
"price": 1.356237,
"date": "2023-07-06"
},
{
"price": 1.359242,
"date": "2023-07-05"
},
{
"price": 1.361995,
"date": "2023-07-04"
},
{
"price": 1.363089,
"date": "2023-07-03"
},
{
"price": 1.34505,
"date": "2023-06-30"
},
{
"price": 1.343242,
"date": "2023-06-29"
},
{
"price": 1.336297,
"date": "2023-06-28"
},
{
"price": 1.332245,
"date": "2023-06-27"
},
{
"price": 1.342611,
"date": "2023-06-26"
},
{
"price": 1.339211,
"date": "2023-06-23"
},
{
"price": 1.351385,
"date": "2023-06-22"
},
{
"price": 1.35702,
"date": "2023-06-21"
},
{
"price": 1.358663,
"date": "2023-06-20"
},
{
"price": 1.361316,
"date": "2023-06-19"
},
{
"price": 1.368194,
"date": "2023-06-16"
},
{
"price": 1.36001,
"date": "2023-06-15"
},
{
"price": 1.348658,
"date": "2023-06-14"
},
{
"price": 1.331171,
"date": "2023-06-13"
},
{
"price": 1.336393,
"date": "2023-06-12"
},
{
"price": 1.338505,
"date": "2023-06-09"
},
{
"price": 1.326742,
"date": "2023-06-07"
},
{
"price": 1.326894,
"date": "2023-06-06"
},
{
"price": 1.314301,
"date": "2023-06-05"
},
{
"price": 1.31711,
"date": "2023-06-02"
},
{
"price": 1.281364,
"date": "2023-06-01"
},
{
"price": 1.267816,
"date": "2023-05-31"
},
{
"price": 1.288142,
"date": "2023-05-30"
},
{
"price": 1.308168,
"date": "2023-05-26"
},
{
"price": 1.298707,
"date": "2023-05-25"
},
{
"price": 1.30148,
"date": "2023-05-24"
},
{
"price": 1.320171,
"date": "2023-05-23"
},
{
"price": 1.314956,
"date": "2023-05-22"
},
{
"price": 1.312909,
"date": "2023-05-19"
},
{
"price": 1.290191,
"date": "2023-05-18"
},
{
"price": 1.281647,
"date": "2023-05-17"
},
{
"price": 1.28216,
"date": "2023-05-16"
},
{
"price": 1.276376,
"date": "2023-05-15"
},
{
"price": 1.279081,
"date": "2023-05-12"
},
{
"price": 1.275893,
"date": "2023-05-11"
},
{
"price": 1.280655,
"date": "2023-05-10"
},
{
"price": 1.284547,
"date": "2023-05-09"
},
{
"price": 1.291525,
"date": "2023-05-08"
},
{
"price": 1.283142,
"date": "2023-05-05"
},
{
"price": 1.2687,
"date": "2023-05-04"
},
{
"price": 1.271998,
"date": "2023-05-02"
},
{
"price": 1.275073,
"date": "2023-04-28"
},
{
"price": 1.286003,
"date": "2023-04-27"
},
{
"price": 1.270632,
"date": "2023-04-26"
},
{
"price": 1.275963,
"date": "2023-04-25"
},
{
"price": 1.284057,
"date": "2023-04-24"
},
{
"price": 1.284258,
"date": "2023-04-21"
},
{
"price": 1.284973,
"date": "2023-04-20"
},
{
"price": 1.279593,
"date": "2023-04-19"
},
{
"price": 1.268247,
"date": "2023-04-18"
},
{
"price": 1.258238,
"date": "2023-04-17"
},
{
"price": 1.258085,
"date": "2023-04-14"
},
{
"price": 1.247934,
"date": "2023-04-13"
},
{
"price": 1.243719,
"date": "2023-04-12"
},
{
"price": 1.242392,
"date": "2023-04-11"
},
{
"price": 1.229046,
"date": "2023-04-06"
},
{
"price": 1.222701,
"date": "2023-04-05"
},
{
"price": 1.2219,
"date": "2023-04-04"
},
{
"price": 1.22438,
"date": "2023-04-03"
},
{
"price": 1.216852,
"date": "2023-03-31"
},
{
"price": 1.210683,
"date": "2023-03-30"
},
{
"price": 1.188308,
"date": "2023-03-29"
},
{
"price": 1.187487,
"date": "2023-03-28"
},
{
"price": 1.185204,
"date": "2023-03-27"
},
{
"price": 1.174622,
"date": "2023-03-24"
},
{
"price": 1.209125,
"date": "2023-03-23"
},
{
"price": 1.221243,
"date": "2023-03-22"
},
{
"price": 1.231746,
"date": "2023-03-21"
},
{
"price": 1.212429,
"date": "2023-03-20"
},
{
"price": 1.209523,
"date": "2023-03-17"
},
{
"price": 1.222573,
"date": "2023-03-16"
},
{
"price": 1.243104,
"date": "2023-03-14"
},
{
"price": 1.245881,
"date": "2023-03-13"
},
{
"price": 1.257203,
"date": "2023-03-10"
},
{
"price": 1.262364,
"date": "2023-03-09"
},
{
"price": 1.278832,
"date": "2023-03-08"
},
{
"price": 1.269309,
"date": "2023-03-07"
},
{
"price": 1.287085,
"date": "2023-03-06"
},
{
"price": 1.278116,
"date": "2023-03-03"
},
{
"price": 1.256442,
"date": "2023-03-02"
},
{
"price": 1.272049,
"date": "2023-03-01"
},
{
"price": 1.278414,
"date": "2023-02-28"
},
{
"price": 1.256961,
"date": "2023-02-27"
},
{
"price": 1.260577,
"date": "2023-02-24"
},
{
"price": 1.257918,
"date": "2023-02-23"
},
{
"price": 1.252239,
"date": "2023-02-22"
},
{
"price": 1.269834,
"date": "2023-02-21"
},
{
"price": 1.271606,
"date": "2023-02-20"
},
{
"price": 1.286242,
"date": "2023-02-17"
},
{
"price": 1.287389,
"date": "2023-02-16"
},
{
"price": 1.283938,
"date": "2023-02-15"
},
{
"price": 1.285782,
"date": "2023-02-14"
},
{
"price": 1.29603,
"date": "2023-02-13"
},
{
"price": 1.290952,
"date": "2023-02-10"
},
{
"price": 1.30176,
"date": "2023-02-09"
},
{
"price": 1.302221,
"date": "2023-02-08"
},
{
"price": 1.298078,
"date": "2023-02-07"
},
{
"price": 1.283909,
"date": "2023-02-06"
},
{
"price": 1.301797,
"date": "2023-02-03"
},
{
"price": 1.297627,
"date": "2023-02-02"
},
{
"price": 1.292256,
"date": "2023-02-01"
},
{
"price": 1.294031,
"date": "2023-01-31"
},
{
"price": 1.297715,
"date": "2023-01-30"
},
{
"price": 1.301664,
"date": "2023-01-27"
},
{
"price": 1.301209,
"date": "2023-01-26"
},
{
"price": 1.291887,
"date": "2023-01-25"
},
{
"price": 1.311215,
"date": "2023-01-24"
},
{
"price": 1.320277,
"date": "2023-01-23"
},
{
"price": 1.303926,
"date": "2023-01-20"
},
{
"price": 1.298428,
"date": "2023-01-19"
},
{
"price": 1.305329,
"date": "2023-01-18"
},
{
"price": 1.310187,
"date": "2023-01-17"
},
{
"price": 1.326786,
"date": "2023-01-16"
},
{
"price": 1.317487,
"date": "2023-01-13"
},
{
"price": 1.332219,
"date": "2023-01-12"
},
{
"price": 1.32333,
"date": "2023-01-11"
},
{
"price": 1.318147,
"date": "2023-01-10"
},
{
"price": 1.309403,
"date": "2023-01-09"
},
{
"price": 1.278847,
"date": "2023-01-05"
},
{
"price": 1.281138,
"date": "2023-01-04"
},
{
"price": 1.274879,
"date": "2023-01-03"
},
{
"price": 1.244156,
"date": "2023-01-02"
},
{
"price": 1.24432,
"date": "2022-12-30"
},
{
"price": 1.255895,
"date": "2022-12-29"
},
{
"price": 1.24806,
"date": "2022-12-28"
},
{
"price": 1.253714,
"date": "2022-12-27"
},
{
"price": 1.258531,
"date": "2022-12-23"
},
{
"price": 1.266436,
"date": "2022-12-22"
},
{
"price": 1.268721,
"date": "2022-12-21"
},
{
"price": 1.256235,
"date": "2022-12-20"
},
{
"price": 1.243661,
"date": "2022-12-19"
},
{
"price": 1.242015,
"date": "2022-12-16"
},
{
"price": 1.24534,
"date": "2022-12-15"
},
{
"price": 1.260612,
"date": "2022-12-14"
},
{
"price": 1.262606,
"date": "2022-12-13"
},
{
"price": 1.269696,
"date": "2022-12-12"
},
{
"price": 1.257527,
"date": "2022-12-09"
},
{
"price": 1.249174,
"date": "2022-12-08"
},
{
"price": 1.244981,
"date": "2022-12-07"
},
{
"price": 1.260851,
"date": "2022-12-06"
},
{
"price": 1.253863,
"date": "2022-12-05"
},
{
"price": 1.247706,
"date": "2022-12-02"
},
{
"price": 1.268501,
"date": "2022-12-01"
},
{
"price": 1.250566,
"date": "2022-11-30"
},
{
"price": 1.250814,
"date": "2022-11-29"
},
{
"price": 1.245831,
"date": "2022-11-28"
},
{
"price": 1.267868,
"date": "2022-11-25"
},
{
"price": 1.272032,
"date": "2022-11-24"
},
{
"price": 1.237019,
"date": "2022-11-23"
},
{
"price": 1.238469,
"date": "2022-11-22"
},
{
"price": 1.233057,
"date": "2022-11-21"
},
{
"price": 1.238081,
"date": "2022-11-18"
},
{
"price": 1.237991,
"date": "2022-11-17"
},
{
"price": 1.237723,
"date": "2022-11-16"
},
{
"price": 1.245835,
"date": "2022-11-15"
},
{
"price": 1.237477,
"date": "2022-11-14"
},
{
"price": 1.187672,
"date": "2022-11-10"
},
{
"price": 1.189178,
"date": "2022-11-09"
},
{
"price": 1.180596,
"date": "2022-11-08"
},
{
"price": 1.167645,
"date": "2022-11-07"
},
{
"price": 1.151626,
"date": "2022-11-04"
},
{
"price": 1.139008,
"date": "2022-11-03"
},
{
"price": 1.141776,
"date": "2022-11-02"
},
{
"price": 1.130051,
"date": "2022-10-28"
},
{
"price": 1.123299,
"date": "2022-10-27"
},
{
"price": 1.112401,
"date": "2022-10-26"
},
{
"price": 1.101903,
"date": "2022-10-25"
},
{
"price": 1.095365,
"date": "2022-10-24"
},
{
"price": 1.09483,
"date": "2022-10-21"
},
{
"price": 1.094297,
"date": "2022-10-20"
},
{
"price": 1.075893,
"date": "2022-10-19"
},
{
"price": 1.094043,
"date": "2022-10-18"
},
{
"price": 1.07996,
"date": "2022-10-17"
},
{
"price": 1.081837,
"date": "2022-10-14"
},
{
"price": 1.092681,
"date": "2022-10-13"
},
{
"price": 1.092303,
"date": "2022-10-12"
},
{
"price": 1.08319,
"date": "2022-10-11"
},
{
"price": 1.090485,
"date": "2022-10-10"
},
{
"price": 1.095674,
"date": "2022-10-07"
},
{
"price": 1.102025,
"date": "2022-10-06"
},
{
"price": 1.099907,
"date": "2022-10-05"
},
{
"price": 1.10494,
"date": "2022-10-04"
},
{
"price": 1.075649,
"date": "2022-10-03"
},
{
"price": 1.058012,
"date": "2022-09-30"
},
{
"price": 1.049753,
"date": "2022-09-29"
},
{
"price": 1.058526,
"date": "2022-09-28"
},
{
"price": 1.064323,
"date": "2022-09-27"
},
{
"price": 1.055698,
"date": "2022-09-26"
},
{
"price": 1.074057,
"date": "2022-09-23"
},
{
"price": 1.10394,
"date": "2022-09-22"
},
{
"price": 1.095829,
"date": "2022-09-21"
},
{
"price": 1.097766,
"date": "2022-09-20"
},
{
"price": 1.118185,
"date": "2022-09-19"
},
{
"price": 1.127357,
"date": "2022-09-16"
},
{
"price": 1.146327,
"date": "2022-09-15"
},
{
"price": 1.132932,
"date": "2022-09-14"
},
{
"price": 1.124843,
"date": "2022-09-13"
},
{
"price": 1.125209,
"date": "2022-09-12"
},
{
"price": 1.110877,
"date": "2022-09-09"
},
{
"price": 1.093831,
"date": "2022-09-08"
},
{
"price": 1.098558,
"date": "2022-09-07"
},
{
"price": 1.09392,
"date": "2022-09-06"
},
{
"price": 1.101831,
"date": "2022-09-05"
},
{
"price": 1.100815,
"date": "2022-09-02"
},
{
"price": 1.094046,
"date": "2022-09-01"
},
{
"price": 1.129731,
"date": "2022-08-31"
},
{
"price": 1.131709,
"date": "2022-08-30"
},
{
"price": 1.148734,
"date": "2022-08-29"
},
{
"price": 1.161977,
"date": "2022-08-26"
},
{
"price": 1.165528,
"date": "2022-08-25"
},
{
"price": 1.17046,
"date": "2022-08-24"
},
{
"price": 1.181624,
"date": "2022-08-23"
},
{
"price": 1.167917,
"date": "2022-08-22"
},
{
"price": 1.191738,
"date": "2022-08-19"
},
{
"price": 1.199598,
"date": "2022-08-18"
},
{
"price": 1.192541,
"date": "2022-08-17"
},
{
"price": 1.216113,
"date": "2022-08-16"
},
{
"price": 1.202631,
"date": "2022-08-12"
},
{
"price": 1.207771,
"date": "2022-08-11"
},
{
"price": 1.200445,
"date": "2022-08-10"
},
{
"price": 1.183105,
"date": "2022-08-09"
},
{
"price": 1.18232,
"date": "2022-08-08"
},
{
"price": 1.170725,
"date": "2022-08-05"
},
{
"price": 1.176358,
"date": "2022-08-04"
},
{
"price": 1.173853,
"date": "2022-08-03"
},
{
"price": 1.170435,
"date": "2022-08-02"
},
{
"price": 1.188742,
"date": "2022-08-01"
},
{
"price": 1.194088,
"date": "2022-07-29"
},
{
"price": 1.187691,
"date": "2022-07-28"
},
{
"price": 1.181383,
"date": "2022-07-27"
},
{
"price": 1.165768,
"date": "2022-07-26"
},
{
"price": 1.165869,
"date": "2022-07-25"
},
{
"price": 1.169095,
"date": "2022-07-22"
},
{
"price": 1.174993,
"date": "2022-07-21"
},
{
"price": 1.162242,
"date": "2022-07-20"
},
{
"price": 1.164399,
"date": "2022-07-19"
},
{
"price": 1.16768,
"date": "2022-07-18"
},
{
"price": 1.144679,
"date": "2022-07-15"
},
{
"price": 1.146509,
"date": "2022-07-14"
},
{
"price": 1.157864,
"date": "2022-07-13"
},
{
"price": 1.162813,
"date": "2022-07-12"
},
{
"price": 1.175089,
"date": "2022-07-11"
},
{
"price": 1.17065,
"date": "2022-07-08"
},
{
"price": 1.164141,
"date": "2022-07-07"
},
{
"price": 1.156513,
"date": "2022-07-06"
},
{
"price": 1.141803,
"date": "2022-07-05"
},
{
"price": 1.145565,
"date": "2022-07-04"
},
{
"price": 1.150915,
"date": "2022-07-01"
},
{
"price": 1.154521,
"date": "2022-06-30"
},
{
"price": 1.178797,
"date": "2022-06-29"
},
{
"price": 1.195962,
"date": "2022-06-28"
},
{
"price": 1.182943,
"date": "2022-06-27"
},
{
"price": 1.181503,
"date": "2022-06-24"
},
{
"price": 1.163662,
"date": "2022-06-23"
},
{
"price": 1.177755,
"date": "2022-06-22"
},
{
"price": 1.198617,
"date": "2022-06-21"
},
{
"price": 1.190434,
"date": "2022-06-20"
},
{
"price": 1.174357,
"date": "2022-06-17"
},
{
"price": 1.187433,
"date": "2022-06-15"
},
{
"price": 1.17803,
"date": "2022-06-14"
},
{
"price": 1.179363,
"date": "2022-06-13"
},
{
"price": 1.200202,
"date": "2022-06-10"
},
{
"price": 1.220306,
"date": "2022-06-09"
},
{
"price": 1.220134,
"date": "2022-06-08"
},
{
"price": 1.22693,
"date": "2022-06-07"
},
{
"price": 1.228544,
"date": "2022-06-03"
},
{
"price": 1.233177,
"date": "2022-06-02"
},
{
"price": 1.230317,
"date": "2022-06-01"
},
{
"price": 1.222611,
"date": "2022-05-31"
},
{
"price": 1.222506,
"date": "2022-05-30"
},
{
"price": 1.202094,
"date": "2022-05-27"
},
{
"price": 1.209965,
"date": "2022-05-26"
},
{
"price": 1.204155,
"date": "2022-05-25"
},
{
"price": 1.199864,
"date": "2022-05-24"
},
{
"price": 1.209985,
"date": "2022-05-23"
},
{
"price": 1.18797,
"date": "2022-05-20"
},
{
"price": 1.187808,
"date": "2022-05-19"
},
{
"price": 1.193118,
"date": "2022-05-18"
},
{
"price": 1.183952,
"date": "2022-05-17"
},
{
"price": 1.156472,
"date": "2022-05-16"
},
{
"price": 1.155152,
"date": "2022-05-13"
},
{
"price": 1.118963,
"date": "2022-05-12"
},
{
"price": 1.129461,
"date": "2022-05-11"
},
{
"price": 1.127528,
"date": "2022-05-10"
},
{
"price": 1.145374,
"date": "2022-05-09"
},
{
"price": 1.154853,
"date": "2022-05-06"
},
{
"price": 1.16255,
"date": "2022-05-05"
},
{
"price": 1.179916,
"date": "2022-05-04"
},
{
"price": 1.178231,
"date": "2022-05-02"
},
{
"price": 1.193011,
"date": "2022-04-29"
},
{
"price": 1.205099,
"date": "2022-04-28"
},
{
"price": 1.202434,
"date": "2022-04-27"
},
{
"price": 1.196176,
"date": "2022-04-26"
},
{
"price": 1.202377,
"date": "2022-04-25"
},
{
"price": 1.224992,
"date": "2022-04-22"
},
{
"price": 1.242272,
"date": "2022-04-21"
},
{
"price": 1.237931,
"date": "2022-04-20"
},
{
"price": 1.249619,
"date": "2022-04-19"
},
{
"price": 1.265892,
"date": "2022-04-14"
},
{
"price": 1.269937,
"date": "2022-04-13"
},
{
"price": 1.260343,
"date": "2022-04-12"
},
{
"price": 1.278213,
"date": "2022-04-11"
},
{
"price": 1.264691,
"date": "2022-04-08"
},
{
"price": 1.260323,
"date": "2022-04-07"
},
{
"price": 1.263697,
"date": "2022-04-06"
},
{
"price": 1.274255,
"date": "2022-04-05"
},
{
"price": 1.289264,
"date": "2022-04-04"
},
{
"price": 1.285717,
"date": "2022-04-01"
},
{
"price": 1.271246,
"date": "2022-03-31"
},
{
"price": 1.284241,
"date": "2022-03-30"
},
{
"price": 1.294931,
"date": "2022-03-29"
},
{
"price": 1.2638,
"date": "2022-03-28"
},
{
"price": 1.255081,
"date": "2022-03-25"
},
{
"price": 1.259292,
"date": "2022-03-24"
},
{
"price": 1.261635,
"date": "2022-03-23"
},
{
"price": 1.276728,
"date": "2022-03-22"
},
{
"price": 1.266619,
"date": "2022-03-21"
},
{
"price": 1.263393,
"date": "2022-03-18"
},
{
"price": 1.263704,
"date": "2022-03-17"
},
{
"price": 1.247525,
"date": "2022-03-16"
},
{
"price": 1.208819,
"date": "2022-03-11"
},
{
"price": 1.179524,
"date": "2022-03-10"
},
{
"price": 1.194898,
"date": "2022-03-09"
},
{
"price": 1.138375,
"date": "2022-03-08"
},
{
"price": 1.125786,
"date": "2022-03-07"
},
{
"price": 1.147613,
"date": "2022-03-04"
},
{
"price": 1.20275,
"date": "2022-03-03"
},
{
"price": 1.200841,
"date": "2022-03-02"
},
{
"price": 1.192421,
"date": "2022-03-01"
},
{
"price": 1.227557,
"date": "2022-02-28"
},
{
"price": 1.254368,
"date": "2022-02-25"
},
{
"price": 1.180586,
"date": "2022-02-24"
},
{
"price": 1.276402,
"date": "2022-02-23"
},
{
"price": 1.288746,
"date": "2022-02-22"
},
{
"price": 1.290986,
"date": "2022-02-21"
},
{
"price": 1.331822,
"date": "2022-02-18"
},
{
"price": 1.349768,
"date": "2022-02-17"
},
{
"price": 1.36712,
"date": "2022-02-16"
},
{
"price": 1.365224,
"date": "2022-02-15"
},
{
"price": 1.343438,
"date": "2022-02-14"
},
{
"price": 1.36723,
"date": "2022-02-11"
},
{
"price": 1.385715,
"date": "2022-02-10"
},
{
"price": 1.384473,
"date": "2022-02-09"
},
{
"price": 1.37108,
"date": "2022-02-08"
},
{
"price": 1.346591,
"date": "2022-02-07"
},
{
"price": 1.34892,
"date": "2022-02-04"
},
{
"price": 1.367194,
"date": "2022-02-03"
},
{
"price": 1.373373,
"date": "2022-02-02"
},
{
"price": 1.358934,
"date": "2022-02-01"
},
{
"price": 1.356099,
"date": "2022-01-31"
},
{
"price": 1.342229,
"date": "2022-01-28"
},
{
"price": 1.362188,
"date": "2022-01-27"
},
{
"price": 1.348987,
"date": "2022-01-26"
},
{
"price": 1.333587,
"date": "2022-01-25"
},
{
"price": 1.322337,
"date": "2022-01-24"
},
{
"price": 1.36062,
"date": "2022-01-21"
},
{
"price": 1.382229,
"date": "2022-01-20"
},
{
"price": 1.381597,
"date": "2022-01-19"
},
{
"price": 1.384063,
"date": "2022-01-18"
},
{
"price": 1.40002,
"date": "2022-01-17"
},
{
"price": 1.398654,
"date": "2022-01-14"
},
{
"price": 1.403441,
"date": "2022-01-13"
},
{
"price": 1.408133,
"date": "2022-01-12"
},
{
"price": 1.382703,
"date": "2022-01-11"
},
{
"price": 1.35865,
"date": "2022-01-10"
},
{
"price": 1.364609,
"date": "2022-01-07"
},
{
"price": 1.367963,
"date": "2022-01-06"
},
{
"price": 1.371155,
"date": "2022-01-05"
},
{
"price": 1.379558,
"date": "2022-01-04"
},
{
"price": 1.37237,
"date": "2022-01-03"
},
{
"price": 1.36569,
"date": "2021-12-31"
},
{
"price": 1.365814,
"date": "2021-12-30"
},
{
"price": 1.36423,
"date": "2021-12-29"
},
{
"price": 1.359285,
"date": "2021-12-28"
},
{
"price": 1.353661,
"date": "2021-12-27"
},
{
"price": 1.34424,
"date": "2021-12-23"
},
{
"price": 1.331052,
"date": "2021-12-22"
},
{
"price": 1.325602,
"date": "2021-12-21"
},
{
"price": 1.314542,
"date": "2021-12-20"
},
{
"price": 1.322242,
"date": "2021-12-17"
},
{
"price": 1.329626,
"date": "2021-12-16"
},
{
"price": 1.307932,
"date": "2021-12-15"
},
{
"price": 1.317432,
"date": "2021-12-14"
},
{
"price": 1.323123,
"date": "2021-12-13"
},
{
"price": 1.327894,
"date": "2021-12-10"
},
{
"price": 1.333858,
"date": "2021-12-09"
},
{
"price": 1.342981,
"date": "2021-12-08"
},
{
"price": 1.337976,
"date": "2021-12-07"
},
{
"price": 1.312115,
"date": "2021-12-06"
},
{
"price": 1.307188,
"date": "2021-12-03"
},
{
"price": 1.306495,
"date": "2021-12-02"
},
{
"price": 1.313638,
"date": "2021-12-01"
},
{
"price": 1.307846,
"date": "2021-11-30"
},
{
"price": 1.305446,
"date": "2021-11-29"
},
{
"price": 1.292649,
"date": "2021-11-26"
},
{
"price": 1.333831,
"date": "2021-11-25"
},
{
"price": 1.335366,
"date": "2021-11-24"
},
{
"price": 1.339809,
"date": "2021-11-23"
},
{
"price": 1.325944,
"date": "2021-11-22"
},
{
"price": 1.319111,
"date": "2021-11-19"
},
{
"price": 1.335945,
"date": "2021-11-18"
},
{
"price": 1.353855,
"date": "2021-11-17"
},
{
"price": 1.362223,
"date": "2021-11-16"
},
{
"price": 1.366033,
"date": "2021-11-15"
},
{
"price": 1.363159,
"date": "2021-11-12"
},
{
"price": 1.371633,
"date": "2021-11-11"
},
{
"price": 1.361987,
"date": "2021-11-10"
},
{
"price": 1.375677,
"date": "2021-11-09"
},
{
"price": 1.378491,
"date": "2021-11-08"
},
{
"price": 1.378652,
"date": "2021-11-05"
},
{
"price": 1.374736,
"date": "2021-11-04"
},
{
"price": 1.352614,
"date": "2021-11-03"
},
{
"price": 1.349984,
"date": "2021-11-02"
},
{
"price": 1.343893,
"date": "2021-10-29"
},
{
"price": 1.344721,
"date": "2021-10-28"
},
{
"price": 1.365314,
"date": "2021-10-27"
},
{
"price": 1.372936,
"date": "2021-10-26"
},
{
"price": 1.367794,
"date": "2021-10-25"
},
{
"price": 1.36366,
"date": "2021-10-22"
},
{
"price": 1.363571,
"date": "2021-10-21"
},
{
"price": 1.375344,
"date": "2021-10-20"
},
{
"price": 1.367926,
"date": "2021-10-19"
},
{
"price": 1.375886,
"date": "2021-10-18"
},
{
"price": 1.37448,
"date": "2021-10-15"
},
{
"price": 1.381308,
"date": "2021-10-14"
},
{
"price": 1.377304,
"date": "2021-10-13"
},
{
"price": 1.384463,
"date": "2021-10-12"
},
{
"price": 1.386636,
"date": "2021-10-11"
},
{
"price": 1.364563,
"date": "2021-10-08"
},
{
"price": 1.355903,
"date": "2021-10-07"
},
{
"price": 1.346974,
"date": "2021-10-06"
},
{
"price": 1.340737,
"date": "2021-10-05"
},
{
"price": 1.325878,
"date": "2021-10-04"
},
{
"price": 1.331351,
"date": "2021-10-01"
},
{
"price": 1.318649,
"date": "2021-09-30"
},
{
"price": 1.306371,
"date": "2021-09-29"
},
{
"price": 1.298745,
"date": "2021-09-28"
},
{
"price": 1.307253,
"date": "2021-09-27"
},
{
"price": 1.295972,
"date": "2021-09-24"
},
{
"price": 1.301232,
"date": "2021-09-23"
},
{
"price": 1.287247,
"date": "2021-09-22"
},
{
"price": 1.266728,
"date": "2021-09-21"
},
{
"price": 1.265869,
"date": "2021-09-20"
},
{
"price": 1.292218,
"date": "2021-09-17"
},
{
"price": 1.290579,
"date": "2021-09-16"
},
{
"price": 1.292787,
"date": "2021-09-15"
},
{
"price": 1.299231,
"date": "2021-09-14"
},
{
"price": 1.301473,
"date": "2021-09-13"
},
{
"price": 1.294365,
"date": "2021-09-10"
},
{
"price": 1.298027,
"date": "2021-09-09"
},
{
"price": 1.297047,
"date": "2021-09-08"
},
{
"price": 1.296729,
"date": "2021-09-07"
},
{
"price": 1.301363,
"date": "2021-09-06"
},
{
"price": 1.295139,
"date": "2021-09-03"
},
{
"price": 1.289886,
"date": "2021-09-02"
},
{
"price": 1.28725,
"date": "2021-09-01"
},
{
"price": 1.278361,
"date": "2021-08-31"
},
{
"price": 1.272189,
"date": "2021-08-30"
},
{
"price": 1.271131,
"date": "2021-08-27"
},
{
"price": 1.257992,
"date": "2021-08-26"
},
{
"price": 1.263131,
"date": "2021-08-25"
},
{
"price": 1.263722,
"date": "2021-08-24"
},
{
"price": 1.261616,
"date": "2021-08-23"
},
{
"price": 1.258282,
"date": "2021-08-19"
},
{
"price": 1.278443,
"date": "2021-08-18"
},
{
"price": 1.278473,
"date": "2021-08-17"
},
{
"price": 1.265768,
"date": "2021-08-16"
},
{
"price": 1.274524,
"date": "2021-08-13"
},
{
"price": 1.270759,
"date": "2021-08-12"
},
{
"price": 1.275086,
"date": "2021-08-11"
},
{
"price": 1.258972,
"date": "2021-08-10"
},
{
"price": 1.263811,
"date": "2021-08-09"
},
{
"price": 1.258987,
"date": "2021-08-06"
},
{
"price": 1.257287,
"date": "2021-08-05"
},
{
"price": 1.259258,
"date": "2021-08-04"
},
{
"price": 1.249751,
"date": "2021-08-03"
},
{
"price": 1.25245,
"date": "2021-08-02"
},
{
"price": 1.248121,
"date": "2021-07-30"
},
{
"price": 1.249722,
"date": "2021-07-29"
},
{
"price": 1.237847,
"date": "2021-07-28"
},
{
"price": 1.237924,
"date": "2021-07-27"
},
{
"price": 1.242096,
"date": "2021-07-26"
},
{
"price": 1.23317,
"date": "2021-07-23"
},
{
"price": 1.233004,
"date": "2021-07-22"
},
{
"price": 1.23547,
"date": "2021-07-21"
},
{
"price": 1.224318,
"date": "2021-07-20"
},
{
"price": 1.221336,
"date": "2021-07-19"
},
{
"price": 1.244734,
"date": "2021-07-16"
},
{
"price": 1.243125,
"date": "2021-07-15"
},
{
"price": 1.229582,
"date": "2021-07-14"
},
{
"price": 1.222636,
"date": "2021-07-13"
},
{
"price": 1.22063,
"date": "2021-07-12"
},
{
"price": 1.221683,
"date": "2021-07-09"
},
{
"price": 1.21651,
"date": "2021-07-08"
},
{
"price": 1.224855,
"date": "2021-07-07"
},
{
"price": 1.213475,
"date": "2021-07-06"
},
{
"price": 1.217872,
"date": "2021-07-05"
},
{
"price": 1.21443,
"date": "2021-07-02"
},
{
"price": 1.217386,
"date": "2021-07-01"
},
{
"price": 1.205787,
"date": "2021-06-30"
},
{
"price": 1.22222,
"date": "2021-06-29"
},
{
"price": 1.232584,
"date": "2021-06-28"
},
{
"price": 1.234038,
"date": "2021-06-25"
},
{
"price": 1.226865,
"date": "2021-06-24"
},
{
"price": 1.217016,
"date": "2021-06-23"
},
{
"price": 1.220042,
"date": "2021-06-22"
},
{
"price": 1.228569,
"date": "2021-06-21"
},
{
"price": 1.226122,
"date": "2021-06-18"
},
{
"price": 1.232001,
"date": "2021-06-17"
},
{
"price": 1.228144,
"date": "2021-06-16"
},
{
"price": 1.238109,
"date": "2021-06-15"
},
{
"price": 1.23955,
"date": "2021-06-14"
},
{
"price": 1.224173,
"date": "2021-06-11"
},
{
"price": 1.222103,
"date": "2021-06-10"
},
{
"price": 1.216736,
"date": "2021-06-09"
},
{
"price": 1.220458,
"date": "2021-06-08"
},
{
"price": 1.21763,
"date": "2021-06-07"
},
{
"price": 1.226093,
"date": "2021-06-04"
},
{
"price": 1.22022,
"date": "2021-06-03"
},
{
"price": 1.215664,
"date": "2021-06-02"
},
{
"price": 1.210243,
"date": "2021-06-01"
},
{
"price": 1.206034,
"date": "2021-05-31"
},
{
"price": 1.204212,
"date": "2021-05-28"
},
{
"price": 1.19456,
"date": "2021-05-27"
},
{
"price": 1.192313,
"date": "2021-05-26"
},
{
"price": 1.186949,
"date": "2021-05-25"
},
{
"price": 1.189293,
"date": "2021-05-21"
},
{
"price": 1.181908,
"date": "2021-05-20"
},
{
"price": 1.172189,
"date": "2021-05-19"
},
{
"price": 1.183466,
"date": "2021-05-18"
},
{
"price": 1.179315,
"date": "2021-05-17"
},
{
"price": 1.173903,
"date": "2021-05-14"
},
{
"price": 1.165306,
"date": "2021-05-13"
},
{
"price": 1.161976,
"date": "2021-05-12"
},
{
"price": 1.161118,
"date": "2021-05-11"
},
{
"price": 1.163795,
"date": "2021-05-10"
},
{
"price": 1.156151,
"date": "2021-05-07"
},
{
"price": 1.140203,
"date": "2021-05-06"
},
{
"price": 1.14375,
"date": "2021-05-05"
},
{
"price": 1.132408,
"date": "2021-05-04"
},
{
"price": 1.13323,
"date": "2021-05-03"
},
{
"price": 1.12946,
"date": "2021-04-30"
},
{
"price": 1.13969,
"date": "2021-04-29"
},
{
"price": 1.135971,
"date": "2021-04-28"
},
{
"price": 1.133007,
"date": "2021-04-27"
},
{
"price": 1.132691,
"date": "2021-04-26"
},
{
"price": 1.123237,
"date": "2021-04-23"
},
{
"price": 1.122784,
"date": "2021-04-22"
},
{
"price": 1.116936,
"date": "2021-04-21"
},
{
"price": 1.116754,
"date": "2021-04-20"
},
{
"price": 1.121533,
"date": "2021-04-19"
},
{
"price": 1.125176,
"date": "2021-04-16"
},
{
"price": 1.116317,
"date": "2021-04-15"
},
{
"price": 1.111968,
"date": "2021-04-14"
},
{
"price": 1.104734,
"date": "2021-04-13"
},
{
"price": 1.107354,
"date": "2021-04-12"
},
{
"price": 1.114268,
"date": "2021-04-09"
},
{
"price": 1.119135,
"date": "2021-04-08"
},
{
"price": 1.125219,
"date": "2021-04-07"
},
{
"price": 1.128123,
"date": "2021-04-06"
},
{
"price": 1.118414,
"date": "2021-04-01"
},
{
"price": 1.11427,
"date": "2021-03-31"
},
{
"price": 1.11903,
"date": "2021-03-30"
},
{
"price": 1.115895,
"date": "2021-03-29"
},
{
"price": 1.111691,
"date": "2021-03-26"
},
{
"price": 1.10165,
"date": "2021-03-25"
},
{
"price": 1.113918,
"date": "2021-03-24"
},
{
"price": 1.118451,
"date": "2021-03-23"
},
{
"price": 1.120648,
"date": "2021-03-22"
},
{
"price": 1.12252,
"date": "2021-03-19"
},
{
"price": 1.133792,
"date": "2021-03-18"
},
{
"price": 1.121682,
"date": "2021-03-17"
},
{
"price": 1.130578,
"date": "2021-03-16"
},
{
"price": 1.130524,
"date": "2021-03-12"
},
{
"price": 1.128247,
"date": "2021-03-11"
},
{
"price": 1.12846,
"date": "2021-03-10"
},
{
"price": 1.121448,
"date": "2021-03-09"
},
{
"price": 1.116155,
"date": "2021-03-08"
},
{
"price": 1.104545,
"date": "2021-03-05"
},
{
"price": 1.097716,
"date": "2021-03-04"
},
{
"price": 1.098924,
"date": "2021-03-03"
},
{
"price": 1.109285,
"date": "2021-03-02"
},
{
"price": 1.109672,
"date": "2021-03-01"
},
{
"price": 1.084886,
"date": "2021-02-26"
},
{
"price": 1.100061,
"date": "2021-02-25"
},
{
"price": 1.089363,
"date": "2021-02-24"
},
{
"price": 1.083685,
"date": "2021-02-23"
},
{
"price": 1.09439,
"date": "2021-02-22"
},
{
"price": 1.104664,
"date": "2021-02-19"
},
{
"price": 1.101039,
"date": "2021-02-18"
},
{
"price": 1.10645,
"date": "2021-02-17"
},
{
"price": 1.116207,
"date": "2021-02-16"
},
{
"price": 1.108594,
"date": "2021-02-15"
},
{
"price": 1.09161,
"date": "2021-02-12"
},
{
"price": 1.091579,
"date": "2021-02-11"
},
{
"price": 1.093136,
"date": "2021-02-10"
},
{
"price": 1.104818,
"date": "2021-02-09"
},
{
"price": 1.105473,
"date": "2021-02-08"
},
{
"price": 1.099215,
"date": "2021-02-05"
},
{
"price": 1.086762,
"date": "2021-02-04"
},
{
"price": 1.086145,
"date": "2021-02-03"
},
{
"price": 1.085991,
"date": "2021-02-02"
},
{
"price": 1.085031,
"date": "2021-02-01"
},
{
"price": 1.076203,
"date": "2021-01-29"
},
{
"price": 1.094159,
"date": "2021-01-28"
},
{
"price": 1.081037,
"date": "2021-01-27"
},
{
"price": 1.093369,
"date": "2021-01-26"
},
{
"price": 1.081982,
"date": "2021-01-25"
},
{
"price": 1.084248,
"date": "2021-01-22"
},
{
"price": 1.093474,
"date": "2021-01-21"
},
{
"price": 1.101658,
"date": "2021-01-20"
},
{
"price": 1.10666,
"date": "2021-01-19"
},
{
"price": 1.116729,
"date": "2021-01-18"
},
{
"price": 1.10503,
"date": "2021-01-15"
},
{
"price": 1.123267,
"date": "2021-01-14"
},
{
"price": 1.120597,
"date": "2021-01-13"
},
{
"price": 1.127283,
"date": "2021-01-12"
},
{
"price": 1.129506,
"date": "2021-01-11"
},
{
"price": 1.132304,
"date": "2021-01-08"
},
{
"price": 1.114538,
"date": "2021-01-07"
},
{
"price": 1.088126,
"date": "2021-01-06"
},
{
"price": 1.087394,
"date": "2021-01-05"
},
{
"price": 1.085384,
"date": "2021-01-04"
},
{
"price": 1.080061,
"date": "2020-12-31"
},
{
"price": 1.084917,
"date": "2020-12-30"
},
{
"price": 1.092774,
"date": "2020-12-29"
},
{
"price": 1.089516,
"date": "2020-12-28"
},
{
"price": 1.070456,
"date": "2020-12-23"
},
{
"price": 1.058838,
"date": "2020-12-22"
},
{
"price": 1.041518,
"date": "2020-12-21"
},
{
"price": 1.066496,
"date": "2020-12-18"
},
{
"price": 1.071637,
"date": "2020-12-17"
},
{
"price": 1.06801,
"date": "2020-12-16"
},
{
"price": 1.053547,
"date": "2020-12-15"
},
{
"price": 1.047653,
"date": "2020-12-14"
},
{
"price": 1.048364,
"date": "2020-12-11"
},
{
"price": 1.066804,
"date": "2020-12-10"
},
{
"price": 1.076341,
"date": "2020-12-09"
},
{
"price": 1.063895,
"date": "2020-12-08"
},
{
"price": 1.058747,
"date": "2020-12-07"
},
{
"price": 1.052193,
"date": "2020-12-04"
},
{
"price": 1.032998,
"date": "2020-12-03"
},
{
"price": 1.031325,
"date": "2020-12-02"
},
{
"price": 1.021034,
"date": "2020-12-01"
},
{
"price": 1.016667,
"date": "2020-11-30"
},
{
"price": 1.028942,
"date": "2020-11-27"
},
{
"price": 1.028146,
"date": "2020-11-26"
},
{
"price": 1.026207,
"date": "2020-11-25"
},
{
"price": 1.02683,
"date": "2020-11-24"
},
{
"price": 1.011159,
"date": "2020-11-23"
},
{
"price": 1.000402,
"date": "2020-11-20"
},
{
"price": 0.998061,
"date": "2020-11-19"
},
{
"price": 1.007362,
"date": "2020-11-18"
},
{
"price": 0.992273,
"date": "2020-11-17"
},
{
"price": 0.985679,
"date": "2020-11-16"
},
{
"price": 0.957029,
"date": "2020-11-13"
},
{
"price": 0.959122,
"date": "2020-11-12"
},
{
"price": 0.960883,
"date": "2020-11-11"
},
{
"price": 0.964651,
"date": "2020-11-10"
},
{
"price": 0.945184,
"date": "2020-11-09"
},
{
"price": 0.914709,
"date": "2020-11-06"
},
{
"price": 0.909767,
"date": "2020-11-05"
},
{
"price": 0.905064,
"date": "2020-11-04"
},
{
"price": 0.896557,
"date": "2020-11-03"
},
{
"price": 0.872993,
"date": "2020-11-02"
},
{
"price": 0.859862,
"date": "2020-10-30"
},
{
"price": 0.861833,
"date": "2020-10-29"
},
{
"price": 0.862736,
"date": "2020-10-28"
},
{
"price": 0.883651,
"date": "2020-10-27"
},
{
"price": 0.887703,
"date": "2020-10-26"
},
{
"price": 0.894029,
"date": "2020-10-22"
},
{
"price": 0.894606,
"date": "2020-10-21"
},
{
"price": 0.902193,
"date": "2020-10-20"
},
{
"price": 0.904619,
"date": "2020-10-19"
},
{
"price": 0.90502,
"date": "2020-10-16"
},
{
"price": 0.894529,
"date": "2020-10-15"
},
{
"price": 0.910868,
"date": "2020-10-14"
},
{
"price": 0.897944,
"date": "2020-10-13"
},
{
"price": 0.898168,
"date": "2020-10-12"
},
{
"price": 0.906048,
"date": "2020-10-09"
},
{
"price": 0.911858,
"date": "2020-10-08"
},
{
"price": 0.917463,
"date": "2020-10-07"
},
{
"price": 0.920423,
"date": "2020-10-06"
},
{
"price": 0.91048,
"date": "2020-10-05"
},
{
"price": 0.904035,
"date": "2020-10-02"
},
{
"price": 0.908577,
"date": "2020-10-01"
},
{
"price": 0.917885,
"date": "2020-09-30"
},
{
"price": 0.915077,
"date": "2020-09-29"
},
{
"price": 0.921495,
"date": "2020-09-28"
},
{
"price": 0.899421,
"date": "2020-09-25"
},
{
"price": 0.907663,
"date": "2020-09-24"
},
{
"price": 0.917005,
"date": "2020-09-23"
},
{
"price": 0.912945,
"date": "2020-09-22"
},
{
"price": 0.910615,
"date": "2020-09-21"
},
{
"price": 0.941782,
"date": "2020-09-18"
},
{
"price": 0.950662,
"date": "2020-09-17"
},
{
"price": 0.95251,
"date": "2020-09-16"
},
{
"price": 0.954971,
"date": "2020-09-15"
},
{
"price": 0.963651,
"date": "2020-09-14"
},
{
"price": 0.963483,
"date": "2020-09-11"
},
{
"price": 0.961557,
"date": "2020-09-10"
},
{
"price": 0.962533,
"date": "2020-09-09"
},
{
"price": 0.960754,
"date": "2020-09-08"
},
{
"price": 0.968141,
"date": "2020-09-07"
},
{
"price": 0.959898,
"date": "2020-09-04"
},
{
"price": 0.961285,
"date": "2020-09-03"
},
{
"price": 0.963884,
"date": "2020-09-02"
},
{
"price": 0.960006,
"date": "2020-09-01"
},
{
"price": 0.96042,
"date": "2020-08-31"
},
{
"price": 0.97007,
"date": "2020-08-28"
},
{
"price": 0.977141,
"date": "2020-08-27"
},
{
"price": 0.973491,
"date": "2020-08-26"
},
{
"price": 0.963329,
"date": "2020-08-25"
},
{
"price": 0.963469,
"date": "2020-08-24"
},
{
"price": 0.956877,
"date": "2020-08-19"
},
{
"price": 0.959608,
"date": "2020-08-18"
},
{
"price": 0.964353,
"date": "2020-08-17"
},
{
"price": 0.959832,
"date": "2020-08-14"
},
{
"price": 0.960517,
"date": "2020-08-13"
},
{
"price": 0.965993,
"date": "2020-08-12"
},
{
"price": 0.961309,
"date": "2020-08-11"
},
{
"price": 0.951915,
"date": "2020-08-10"
},
{
"price": 0.946199,
"date": "2020-08-07"
},
{
"price": 0.943179,
"date": "2020-08-06"
},
{
"price": 0.944109,
"date": "2020-08-05"
},
{
"price": 0.932202,
"date": "2020-08-04"
},
{
"price": 0.923338,
"date": "2020-08-03"
},
{
"price": 0.913737,
"date": "2020-07-31"
},
{
"price": 0.916213,
"date": "2020-07-30"
},
{
"price": 0.940898,
"date": "2020-07-29"
},
{
"price": 0.940717,
"date": "2020-07-28"
},
{
"price": 0.942443,
"date": "2020-07-27"
},
{
"price": 0.940387,
"date": "2020-07-24"
},
{
"price": 0.947215,
"date": "2020-07-23"
},
{
"price": 0.9539,
"date": "2020-07-22"
},
{
"price": 0.960742,
"date": "2020-07-21"
},
{
"price": 0.957373,
"date": "2020-07-20"
},
{
"price": 0.94924,
"date": "2020-07-17"
},
{
"price": 0.949332,
"date": "2020-07-16"
},
{
"price": 0.949903,
"date": "2020-07-15"
},
{
"price": 0.939647,
"date": "2020-07-14"
},
{
"price": 0.950702,
"date": "2020-07-13"
},
{
"price": 0.947251,
"date": "2020-07-10"
},
{
"price": 0.949619,
"date": "2020-07-09"
},
{
"price": 0.950399,
"date": "2020-07-08"
},
{
"price": 0.950767,
"date": "2020-07-07"
},
{
"price": 0.95832,
"date": "2020-07-06"
},
{
"price": 0.947219,
"date": "2020-07-03"
},
{
"price": 0.950285,
"date": "2020-07-02"
},
{
"price": 0.941406,
"date": "2020-07-01"
},
{
"price": 0.941826,
"date": "2020-06-30"
},
{
"price": 0.944909,
"date": "2020-06-29"
},
{
"price": 0.937257,
"date": "2020-06-26"
},
{
"price": 0.946332,
"date": "2020-06-25"
},
{
"price": 0.939738,
"date": "2020-06-24"
},
{
"price": 0.951428,
"date": "2020-06-23"
},
{
"price": 0.932491,
"date": "2020-06-22"
},
{
"price": 0.933721,
"date": "2020-06-19"
},
{
"price": 0.932101,
"date": "2020-06-18"
},
{
"price": 0.934913,
"date": "2020-06-17"
},
{
"price": 0.944723,
"date": "2020-06-16"
},
{
"price": 0.921209,
"date": "2020-06-15"
},
{
"price": 0.929298,
"date": "2020-06-12"
},
{
"price": 0.926062,
"date": "2020-06-11"
},
{
"price": 0.943685,
"date": "2020-06-10"
},
{
"price": 0.952445,
"date": "2020-06-09"
},
{
"price": 0.959793,
"date": "2020-06-08"
},
{
"price": 0.960131,
"date": "2020-06-05"
},
{
"price": 0.94361,
"date": "2020-06-04"
},
{
"price": 0.944507,
"date": "2020-06-03"
},
{
"price": 0.924228,
"date": "2020-06-02"
},
{
"price": 0.915394,
"date": "2020-05-29"
},
{
"price": 0.92735,
"date": "2020-05-28"
},
{
"price": 0.92495,
"date": "2020-05-27"
},
{
"price": 0.922807,
"date": "2020-05-26"
},
{
"price": 0.893137,
"date": "2020-05-25"
},
{
"price": 0.885117,
"date": "2020-05-22"
},
{
"price": 0.88467,
"date": "2020-05-21"
},
{
"price": 0.888725,
"date": "2020-05-20"
},
{
"price": 0.884244,
"date": "2020-05-19"
},
{
"price": 0.890586,
"date": "2020-05-18"
},
{
"price": 0.863369,
"date": "2020-05-15"
},
{
"price": 0.861261,
"date": "2020-05-14"
},
{
"price": 0.876272,
"date": "2020-05-13"
},
{
"price": 0.881823,
"date": "2020-05-12"
},
{
"price": 0.871845,
"date": "2020-05-11"
},
{
"price": 0.874693,
"date": "2020-05-08"
},
{
"price": 0.870626,
"date": "2020-05-07"
},
{
"price": 0.861727,
"date": "2020-05-06"
},
{
"price": 0.872888,
"date": "2020-05-05"
},
{
"price": 0.867545,
"date": "2020-05-04"
},
{
"price": 0.882838,
"date": "2020-04-30"
},
{
"price": 0.894229,
"date": "2020-04-29"
},
{
"price": 0.869029,
"date": "2020-04-28"
},
{
"price": 0.859488,
"date": "2020-04-27"
},
{
"price": 0.861718,
"date": "2020-04-24"
},
{
"price": 0.864733,
"date": "2020-04-23"
},
{
"price": 0.848107,
"date": "2020-04-22"
},
{
"price": 0.837311,
"date": "2020-04-21"
},
{
"price": 0.86224,
"date": "2020-04-20"
},
{
"price": 0.856416,
"date": "2020-04-17"
},
{
"price": 0.842865,
"date": "2020-04-16"
},
{
"price": 0.84455,
"date": "2020-04-15"
},
{
"price": 0.873757,
"date": "2020-04-14"
},
{
"price": 0.863035,
"date": "2020-04-09"
},
{
"price": 0.853012,
"date": "2020-04-08"
},
{
"price": 0.855173,
"date": "2020-04-07"
},
{
"price": 0.849249,
"date": "2020-04-06"
},
{
"price": 0.822783,
"date": "2020-04-03"
},
{
"price": 0.822342,
"date": "2020-04-02"
},
{
"price": 0.819117,
"date": "2020-04-01"
},
{
"price": 0.830254,
"date": "2020-03-31"
},
{
"price": 0.809483,
"date": "2020-03-30"
},
{
"price": 0.808419,
"date": "2020-03-27"
},
{
"price": 0.820751,
"date": "2020-03-26"
},
{
"price": 0.807586,
"date": "2020-03-25"
},
{
"price": 0.79951,
"date": "2020-03-24"
},
{
"price": 0.758576,
"date": "2020-03-23"
},
{
"price": 0.77823,
"date": "2020-03-20"
},
{
"price": 0.765028,
"date": "2020-03-19"
},
{
"price": 0.746138,
"date": "2020-03-18"
},
{
"price": 0.773432,
"date": "2020-03-17"
},
{
"price": 0.763656,
"date": "2020-03-16"
},
{
"price": 0.801162,
"date": "2020-03-13"
},
{
"price": 0.779979,
"date": "2020-03-12"
},
{
"price": 0.862347,
"date": "2020-03-11"
},
{
"price": 0.900571,
"date": "2020-03-10"
},
{
"price": 0.90259,
"date": "2020-03-09"
},
{
"price": 0.968306,
"date": "2020-03-06"
},
{
"price": 0.996915,
"date": "2020-03-05"
},
{
"price": 1.010423,
"date": "2020-03-04"
},
{
"price": 1.019623,
"date": "2020-03-03"
},
{
"price": 0.99047,
"date": "2020-03-02"
},
{
"price": 0.97897,
"date": "2020-02-28"
},
{
"price": 1.017745,
"date": "2020-02-27"
},
{
"price": 1.048679,
"date": "2020-02-26"
},
{
"price": 1.044632,
"date": "2020-02-25"
},
{
"price": 1.070841,
"date": "2020-02-24"
},
{
"price": 1.108231,
"date": "2020-02-21"
},
{
"price": 1.114388,
"date": "2020-02-20"
},
{
"price": 1.115065,
"date": "2020-02-19"
},
{
"price": 1.110898,
"date": "2020-02-18"
},
{
"price": 1.111911,
"date": "2020-02-17"
},
{
"price": 1.112026,
"date": "2020-02-14"
},
{
"price": 1.119008,
"date": "2020-02-13"
},
{
"price": 1.11715,
"date": "2020-02-12"
},
{
"price": 1.109078,
"date": "2020-02-11"
},
{
"price": 1.104964,
"date": "2020-02-10"
},
{
"price": 1.112899,
"date": "2020-02-07"
},
{
"price": 1.109496,
"date": "2020-02-06"
},
{
"price": 1.099949,
"date": "2020-02-05"
},
{
"price": 1.090559,
"date": "2020-02-04"
},
{
"price": 1.08208,
"date": "2020-02-03"
},
{
"price": 1.071786,
"date": "2020-01-31"
},
{
"price": 1.07951,
"date": "2020-01-30"
},
{
"price": 1.090219,
"date": "2020-01-29"
},
{
"price": 1.094918,
"date": "2020-01-28"
},
{
"price": 1.100436,
"date": "2020-01-27"
},
{
"price": 1.121906,
"date": "2020-01-24"
},
{
"price": 1.121466,
"date": "2020-01-23"
},
{
"price": 1.116164,
"date": "2020-01-22"
},
{
"price": 1.111882,
"date": "2020-01-21"
},
{
"price": 1.120635,
"date": "2020-01-20"
},
{
"price": 1.11556,
"date": "2020-01-17"
},
{
"price": 1.113436,
"date": "2020-01-16"
},
{
"price": 1.113561,
"date": "2020-01-15"
},
{
"price": 1.120045,
"date": "2020-01-14"
},
{
"price": 1.13203,
"date": "2020-01-13"
},
{
"price": 1.118712,
"date": "2020-01-10"
},
{
"price": 1.10877,
"date": "2020-01-09"
},
{
"price": 1.093416,
"date": "2020-01-08"
},
{
"price": 1.094933,
"date": "2020-01-07"
},
{
"price": 1.097619,
"date": "2020-01-06"
},
{
"price": 1.104051,
"date": "2020-01-03"
},
{
"price": 1.111297,
"date": "2020-01-02"
},
{
"price": 1.098978,
"date": "2019-12-31"
},
{
"price": 1.099475,
"date": "2019-12-30"
},
{
"price": 1.099515,
"date": "2019-12-23"
},
{
"price": 1.091785,
"date": "2019-12-20"
},
{
"price": 1.097887,
"date": "2019-12-19"
},
{
"price": 1.09132,
"date": "2019-12-18"
},
{
"price": 1.084436,
"date": "2019-12-17"
},
{
"price": 1.079313,
"date": "2019-12-16"
},
{
"price": 1.073196,
"date": "2019-12-13"
},
{
"price": 1.069923,
"date": "2019-12-12"
},
{
"price": 1.054205,
"date": "2019-12-11"
},
{
"price": 1.058995,
"date": "2019-12-10"
},
{
"price": 1.066975,
"date": "2019-12-09"
},
{
"price": 1.063479,
"date": "2019-12-06"
},
{
"price": 1.068455,
"date": "2019-12-05"
},
{
"price": 1.066827,
"date": "2019-12-04"
},
{
"price": 1.061916,
"date": "2019-12-03"
},
{
"price": 1.0725,
"date": "2019-12-02"
},
{
"price": 1.084641,
"date": "2019-11-29"
},
{
"price": 1.093271,
"date": "2019-11-28"
},
{
"price": 1.095024,
"date": "2019-11-27"
},
{
"price": 1.096411,
"date": "2019-11-26"
},
{
"price": 1.097125,
"date": "2019-11-25"
},
{
"price": 1.091678,
"date": "2019-11-22"
},
{
"price": 1.083848,
"date": "2019-11-21"
},
{
"price": 1.088251,
"date": "2019-11-20"
},
{
"price": 1.092352,
"date": "2019-11-19"
},
{
"price": 1.097662,
"date": "2019-11-18"
},
{
"price": 1.094989,
"date": "2019-11-15"
},
{
"price": 1.088878,
"date": "2019-11-14"
},
{
"price": 1.096681,
"date": "2019-11-13"
},
{
"price": 1.098452,
"date": "2019-11-12"
},
{
"price": 1.098993,
"date": "2019-11-11"
},
{
"price": 1.097839,
"date": "2019-11-08"
},
{
"price": 1.099755,
"date": "2019-11-07"
},
{
"price": 1.088633,
"date": "2019-11-06"
},
{
"price": 1.087247,
"date": "2019-11-05"
},
{
"price": 1.079376,
"date": "2019-11-04"
},
{
"price": 1.060319,
"date": "2019-10-31"
},
{
"price": 1.074029,
"date": "2019-10-30"
},
{
"price": 1.070228,
"date": "2019-10-29"
},
{
"price": 1.065733,
"date": "2019-10-28"
},
{
"price": 1.060817,
"date": "2019-10-25"
},
{
"price": 1.068057,
"date": "2019-10-24"
},
{
"price": 1.060928,
"date": "2019-10-22"
},
{
"price": 1.052002,
"date": "2019-10-21"
},
{
"price": 1.041535,
"date": "2019-10-18"
},
{
"price": 1.043559,
"date": "2019-10-17"
},
{
"price": 1.03734,
"date": "2019-10-16"
},
{
"price": 1.036884,
"date": "2019-10-15"
},
{
"price": 1.032745,
"date": "2019-10-14"
},
{
"price": 1.030988,
"date": "2019-10-11"
},
{
"price": 1.01793,
"date": "2019-10-10"
},
{
"price": 1.022196,
"date": "2019-10-09"
},
{
"price": 1.016714,
"date": "2019-10-08"
},
{
"price": 1.017524,
"date": "2019-10-07"
},
{
"price": 1.016113,
"date": "2019-10-04"
},
{
"price": 1.010461,
"date": "2019-10-03"
},
{
"price": 1.00859,
"date": "2019-10-02"
},
{
"price": 1.029471,
"date": "2019-10-01"
},
{
"price": 1.039433,
"date": "2019-09-30"
},
{
"price": 1.043919,
"date": "2019-09-27"
},
{
"price": 1.03703,
"date": "2019-09-26"
},
{
"price": 1.034674,
"date": "2019-09-25"
},
{
"price": 1.043711,
"date": "2019-09-24"
},
{
"price": 1.036683,
"date": "2019-09-23"
},
{
"price": 1.044234,
"date": "2019-09-20"
},
{
"price": 1.043603,
"date": "2019-09-19"
},
{
"price": 1.04232,
"date": "2019-09-18"
},
{
"price": 1.038497,
"date": "2019-09-17"
},
{
"price": 1.046682,
"date": "2019-09-16"
},
{
"price": 1.040832,
"date": "2019-09-13"
},
{
"price": 1.031778,
"date": "2019-09-12"
},
{
"price": 1.035261,
"date": "2019-09-11"
},
{
"price": 1.028923,
"date": "2019-09-10"
},
{
"price": 1.025115,
"date": "2019-09-09"
},
{
"price": 1.012142,
"date": "2019-09-06"
},
{
"price": 1.008565,
"date": "2019-09-05"
},
{
"price": 0.997716,
"date": "2019-09-04"
},
{
"price": 0.998975,
"date": "2019-09-03"
},
{
"price": 1.009035,
"date": "2019-09-02"
},
{
"price": 1.008014,
"date": "2019-08-30"
},
{
"price": 0.991104,
"date": "2019-08-29"
},
{
"price": 0.985468,
"date": "2019-08-28"
},
{
"price": 0.99477,
"date": "2019-08-27"
},
{
"price": 0.997739,
"date": "2019-08-26"
},
{
"price": 0.998089,
"date": "2019-08-23"
},
{
"price": 0.99617,
"date": "2019-08-22"
},
{
"price": 0.998678,
"date": "2019-08-21"
},
{
"price": 0.985712,
"date": "2019-08-16"
},
{
"price": 0.98306,
"date": "2019-08-15"
},
{
"price": 0.981685,
"date": "2019-08-14"
},
{
"price": 0.99964,
"date": "2019-08-13"
},
{
"price": 0.994736,
"date": "2019-08-12"
},
{
"price": 0.995595,
"date": "2019-08-09"
},
{
"price": 1.001263,
"date": "2019-08-08"
},
{
"price": 0.994905,
"date": "2019-08-07"
},
{
"price": 0.999144,
"date": "2019-08-06"
},
{
"price": 1.002772,
"date": "2019-08-05"
},
{
"price": 1.021341,
"date": "2019-08-02"
},
{
"price": 1.026711,
"date": "2019-08-01"
},
{
"price": 1.042637,
"date": "2019-07-31"
},
{
"price": 1.04133,
"date": "2019-07-30"
},
{
"price": 1.045941,
"date": "2019-07-29"
},
{
"price": 1.049031,
"date": "2019-07-26"
},
{
"price": 1.05052,
"date": "2019-07-25"
},
{
"price": 1.055981,
"date": "2019-07-24"
},
{
"price": 1.05627,
"date": "2019-07-23"
},
{
"price": 1.052971,
"date": "2019-07-22"
},
{
"price": 1.055901,
"date": "2019-07-19"
},
{
"price": 1.049628,
"date": "2019-07-18"
},
{
"price": 1.045061,
"date": "2019-07-17"
},
{
"price": 1.042678,
"date": "2019-07-16"
},
{
"price": 1.041847,
"date": "2019-07-15"
},
{
"price": 1.038738,
"date": "2019-07-12"
},
{
"price": 1.035942,
"date": "2019-07-11"
},
{
"price": 1.032737,
"date": "2019-07-10"
},
{
"price": 1.03065,
"date": "2019-07-09"
},
{
"price": 1.03892,
"date": "2019-07-08"
},
{
"price": 1.040878,
"date": "2019-07-05"
},
{
"price": 1.038366,
"date": "2019-07-04"
},
{
"price": 1.034509,
"date": "2019-07-03"
},
{
"price": 1.02749,
"date": "2019-07-02"
},
{
"price": 1.02649,
"date": "2019-07-01"
},
{
"price": 1.025143,
"date": "2019-06-28"
},
{
"price": 1.02414,
"date": "2019-06-27"
},
{
"price": 1.016787,
"date": "2019-06-26"
},
{
"price": 1.015268,
"date": "2019-06-25"
},
{
"price": 1.027123,
"date": "2019-06-24"
},
{
"price": 1.022047,
"date": "2019-06-21"
},
{
"price": 1.02622,
"date": "2019-06-20"
},
{
"price": 1.025403,
"date": "2019-06-19"
},
{
"price": 1.021819,
"date": "2019-06-18"
},
{
"price": 1.013898,
"date": "2019-06-17"
},
{
"price": 1.014663,
"date": "2019-06-14"
},
{
"price": 1.01552,
"date": "2019-06-13"
},
{
"price": 1.015586,
"date": "2019-06-12"
},
{
"price": 1.02233,
"date": "2019-06-11"
},
{
"price": 1.014865,
"date": "2019-06-07"
},
{
"price": 1.009024,
"date": "2019-06-06"
},
{
"price": 1.007838,
"date": "2019-06-05"
},
{
"price": 1.006677,
"date": "2019-06-04"
},
{
"price": 1.011837,
"date": "2019-06-03"
},
{
"price": 1.007361,
"date": "2019-05-31"
},
{
"price": 1.006349,
"date": "2019-05-30"
},
{
"price": 1.001037,
"date": "2019-05-29"
},
{
"price": 0.995941,
"date": "2019-05-28"
},
{
"price": 0.988371,
"date": "2019-05-27"
},
{
"price": 0.986233,
"date": "2019-05-24"
},
{
"price": 0.980285,
"date": "2019-05-23"
},
{
"price": 0.987028,
"date": "2019-05-22"
},
{
"price": 0.985698,
"date": "2019-05-21"
},
{
"price": 0.983455,
"date": "2019-05-20"
},
{
"price": 0.984663,
"date": "2019-05-17"
},
{
"price": 0.987079,
"date": "2019-05-16"
},
{
"price": 0.980281,
"date": "2019-05-15"
},
{
"price": 0.977943,
"date": "2019-05-14"
},
{
"price": 0.979558,
"date": "2019-05-13"
},
{
"price": 0.988713,
"date": "2019-05-10"
},
{
"price": 0.98689,
"date": "2019-05-09"
},
{
"price": 1.000701,
"date": "2019-05-08"
},
{
"price": 1.000577,
"date": "2019-05-07"
},
{
"price": 1.009524,
"date": "2019-05-06"
},
{
"price": 1.020482,
"date": "2019-05-03"
},
{
"price": 1.028044,
"date": "2019-05-02"
},
{
"price": 1.023006,
"date": "2019-04-30"
},
{
"price": 1.026216,
"date": "2019-04-29"
},
{
"price": 1.031427,
"date": "2019-04-26"
},
{
"price": 1.02719,
"date": "2019-04-25"
},
{
"price": 1.030154,
"date": "2019-04-24"
},
{
"price": 1.031144,
"date": "2019-04-23"
},
{
"price": 1.027624,
"date": "2019-04-18"
},
{
"price": 1.026421,
"date": "2019-04-17"
},
{
"price": 1.026478,
"date": "2019-04-16"
},
{
"price": 1.028095,
"date": "2019-04-15"
},
{
"price": 1.031885,
"date": "2019-04-12"
},
{
"price": 1.024948,
"date": "2019-04-11"
},
{
"price": 1.014582,
"date": "2019-04-09"
},
{
"price": 1.012356,
"date": "2019-04-08"
},
{
"price": 1.008571,
"date": "2019-04-05"
},
{
"price": 1.008521,
"date": "2019-04-04"
},
{
"price": 1.013801,
"date": "2019-04-03"
},
{
"price": 1.009021,
"date": "2019-04-02"
},
{
"price": 1.004209,
"date": "2019-04-01"
},
{
"price": 0.991758,
"date": "2019-03-29"
},
{
"price": 0.990233,
"date": "2019-03-28"
},
{
"price": 0.991295,
"date": "2019-03-27"
},
{
"price": 0.983707,
"date": "2019-03-26"
},
{
"price": 0.982992,
"date": "2019-03-25"
},
{
"price": 0.985093,
"date": "2019-03-22"
},
{
"price": 0.98987,
"date": "2019-03-21"
},
{
"price": 0.983199,
"date": "2019-03-20"
},
{
"price": 0.983219,
"date": "2019-03-19"
},
{
"price": 0.985407,
"date": "2019-03-18"
},
{
"price": 0.974882,
"date": "2019-03-14"
},
{
"price": 0.969409,
"date": "2019-03-13"
},
{
"price": 0.967038,
"date": "2019-03-12"
},
{
"price": 0.968597,
"date": "2019-03-11"
},
{
"price": 0.964505,
"date": "2019-03-08"
},
{
"price": 0.967998,
"date": "2019-03-07"
},
{
"price": 0.978378,
"date": "2019-03-06"
},
{
"price": 0.977058,
"date": "2019-03-05"
},
{
"price": 0.980687,
"date": "2019-03-04"
},
{
"price": 0.974907,
"date": "2019-03-01"
},
{
"price": 0.97528,
"date": "2019-02-28"
},
{
"price": 0.971401,
"date": "2019-02-27"
},
{
"price": 0.977429,
"date": "2019-02-26"
},
{
"price": 0.978661,
"date": "2019-02-25"
},
{
"price": 0.973044,
"date": "2019-02-22"
},
{
"price": 0.974114,
"date": "2019-02-21"
},
{
"price": 0.980925,
"date": "2019-02-20"
},
{
"price": 0.972088,
"date": "2019-02-19"
},
{
"price": 0.973039,
"date": "2019-02-18"
},
{
"price": 0.969765,
"date": "2019-02-15"
},
{
"price": 0.960295,
"date": "2019-02-14"
},
{
"price": 0.971273,
"date": "2019-02-13"
},
{
"price": 0.974308,
"date": "2019-02-12"
},
{
"price": 0.965924,
"date": "2019-02-11"
},
{
"price": 0.966226,
"date": "2019-02-08"
},
{
"price": 0.976007,
"date": "2019-02-07"
},
{
"price": 0.983011,
"date": "2019-02-06"
},
{
"price": 0.980421,
"date": "2019-02-05"
},
{
"price": 0.974886,
"date": "2019-02-04"
},
{
"price": 0.972004,
"date": "2019-02-01"
},
{
"price": 0.963625,
"date": "2019-01-31"
},
{
"price": 0.967804,
"date": "2019-01-30"
},
{
"price": 0.965165,
"date": "2019-01-29"
},
{
"price": 0.966532,
"date": "2019-01-28"
},
{
"price": 0.971952,
"date": "2019-01-25"
},
{
"price": 0.967187,
"date": "2019-01-24"
},
{
"price": 0.968495,
"date": "2019-01-23"
},
{
"price": 0.961292,
"date": "2019-01-22"
},
{
"price": 0.964054,
"date": "2019-01-21"
},
{
"price": 0.974093,
"date": "2019-01-18"
},
{
"price": 0.974272,
"date": "2019-01-17"
},
{
"price": 0.979865,
"date": "2019-01-16"
},
{
"price": 0.965206,
"date": "2019-01-15"
},
{
"price": 0.959002,
"date": "2019-01-14"
},
{
"price": 0.966852,
"date": "2019-01-11"
},
{
"price": 0.972214,
"date": "2019-01-10"
},
{
"price": 0.975408,
"date": "2019-01-09"
},
{
"price": 0.969919,
"date": "2019-01-08"
},
{
"price": 0.973001,
"date": "2019-01-07"
},
{
"price": 0.962746,
"date": "2019-01-04"
},
{
"price": 0.946799,
"date": "2019-01-03"
},
{
"price": 0.950026,
"date": "2019-01-02"
},
{
"price": 0.941252,
"date": "2018-12-28"
},
{
"price": 0.931981,
"date": "2018-12-27"
},
{
"price": 0.934253,
"date": "2018-12-21"
},
{
"price": 0.950734,
"date": "2018-12-20"
},
{
"price": 0.965982,
"date": "2018-12-19"
},
{
"price": 0.986441,
"date": "2018-12-18"
},
{
"price": 0.984437,
"date": "2018-12-17"
},
{
"price": 0.993354,
"date": "2018-12-14"
},
{
"price": 0.992042,
"date": "2018-12-13"
},
{
"price": 0.987956,
"date": "2018-12-12"
},
{
"price": 0.975155,
"date": "2018-12-11"
},
{
"price": 0.974266,
"date": "2018-12-10"
},
{
"price": 0.988882,
"date": "2018-12-07"
},
{
"price": 0.989856,
"date": "2018-12-06"
},
{
"price": 1.012169,
"date": "2018-12-05"
},
{
"price": 1.015194,
"date": "2018-12-04"
},
{
"price": 1.013347,
"date": "2018-12-03"
},
{
"price": 1.002581,
"date": "2018-11-30"
},
{
"price": 1.003247,
"date": "2018-11-29"
},
{
"price": 0.996296,
"date": "2018-11-28"
},
{
"price": 0.988721,
"date": "2018-11-27"
},
{
"price": 0.983045,
"date": "2018-11-26"
},
{
"price": 0.979244,
"date": "2018-11-23"
},
{
"price": 0.982714,
"date": "2018-11-22"
},
{
"price": 0.983139,
"date": "2018-11-21"
},
{
"price": 0.970321,
"date": "2018-11-20"
},
{
"price": 0.97878,
"date": "2018-11-19"
},
{
"price": 0.979206,
"date": "2018-11-16"
},
{
"price": 0.984214,
"date": "2018-11-15"
},
{
"price": 0.989739,
"date": "2018-11-14"
},
{
"price": 0.983319,
"date": "2018-11-13"
},
{
"price": 0.98302,
"date": "2018-11-12"
},
{
"price": 0.987812,
"date": "2018-11-09"
},
{
"price": 0.988736,
"date": "2018-11-08"
},
{
"price": 0.987671,
"date": "2018-11-07"
},
{
"price": 0.976269,
"date": "2018-11-06"
},
{
"price": 0.97893,
"date": "2018-11-05"
},
{
"price": 0.968485,
"date": "2018-10-31"
},
{
"price": 0.956675,
"date": "2018-10-30"
},
{
"price": 0.95297,
"date": "2018-10-29"
},
{
"price": 0.942624,
"date": "2018-10-26"
},
{
"price": 0.957171,
"date": "2018-10-25"
},
{
"price": 0.95788,
"date": "2018-10-24"
},
{
"price": 0.973969,
"date": "2018-10-19"
},
{
"price": 0.974161,
"date": "2018-10-18"
},
{
"price": 0.978506,
"date": "2018-10-17"
},
{
"price": 0.980713,
"date": "2018-10-16"
},
{
"price": 0.969915,
"date": "2018-10-15"
},
{
"price": 0.970858,
"date": "2018-10-12"
},
{
"price": 0.965243,
"date": "2018-10-11"
},
{
"price": 0.976271,
"date": "2018-10-10"
},
{
"price": 0.984858,
"date": "2018-10-09"
},
{
"price": 0.980702,
"date": "2018-10-08"
},
{
"price": 0.987204,
"date": "2018-10-05"
},
{
"price": 0.988704,
"date": "2018-10-04"
},
{
"price": 0.988718,
"date": "2018-10-03"
},
{
"price": 0.986223,
"date": "2018-10-02"
},
{
"price": 0.98775,
"date": "2018-10-01"
},
{
"price": 0.990056,
"date": "2018-09-28"
},
{
"price": 0.993818,
"date": "2018-09-27"
},
{
"price": 0.988239,
"date": "2018-09-26"
},
{
"price": 0.986871,
"date": "2018-09-25"
},
{
"price": 0.981149,
"date": "2018-09-24"
},
{
"price": 0.981898,
"date": "2018-09-21"
},
{
"price": 0.987207,
"date": "2018-09-20"
},
{
"price": 0.988671,
"date": "2018-09-19"
},
{
"price": 0.983919,
"date": "2018-09-18"
},
{
"price": 0.97802,
"date": "2018-09-17"
},
{
"price": 0.97994,
"date": "2018-09-14"
},
{
"price": 0.981129,
"date": "2018-09-13"
},
{
"price": 0.978252,
"date": "2018-09-12"
},
{
"price": 0.98484,
"date": "2018-09-11"
},
{
"price": 0.989756,
"date": "2018-09-10"
},
{
"price": 0.98735,
"date": "2018-09-07"
},
{
"price": 0.994806,
"date": "2018-09-06"
},
{
"price": 0.998594,
"date": "2018-09-05"
},
{
"price": 0.995645,
"date": "2018-09-04"
},
{
"price": 0.999078,
"date": "2018-09-03"
},
{
"price": 0.996373,
"date": "2018-08-31"
},
{
"price": 0.999829,
"date": "2018-08-30"
},
{
"price": 1.000484,
"date": "2018-08-29"
},
{
"price": 0.999567,
"date": "2018-08-28"
},
{
"price": 0.999656,
"date": "2018-08-27"
},
{
"price": 0.999857,
"date": "2018-08-24"
},
{
"price": 0.999882,
"date": "2018-08-23"
},
{
"price": 0.999646,
"date": "2018-08-22"
},
{
"price": 0.99978,
"date": "2018-08-21"
},
{
"price": 1.0,
"date": "2018-08-17"
},
{
"price": 1.740287,
"date": "2024-08-12"
},
{
"price": 1.742995,
"date": "2024-08-13"
},
{
"price": 1.755497,
"date": "2024-08-14"
},
{
"price": 1.821238,
"date": "2024-08-16"
},
{
"price": 1.788486,
"date": "2024-08-21"
},
{
"price": 1.790273,
"date": "2024-08-22"
},
{
"price": 1.796076,
"date": "2024-08-23"
},
{
"price": 1.796872,
"date": "2024-08-26"
},
{
"price": 1.792046,
"date": "2024-08-27"
},
{
"price": 1.773301,
"date": "2024-08-28"
},
{
"price": 1.791579,
"date": "2024-08-29"
},
{
"price": 1.8002,
"date": "2024-08-30"
},
{
 "price": 1.77791,
 "date": "2024-09-24"
},
{
 "price": 1.787214,
 "date": "2024-09-25"
},
{
 "price": 1.805482,
 "date": "2024-09-26"
},
{
 "price": 1.817883,
 "date": "2024-09-27"
},
{
 "price": 1.777915,
 "date": "2024-09-30"
},
{
 "price": 1.768236,
 "date": "2024-10-01"
},
{
 "price": 1.772364,
 "date": "2024-10-02"
},
{
 "price": 1.749746,
 "date": "2024-10-03"
},
{
 "price": 1.757103,
 "date": "2024-10-04"
},
{
 "price": 1.751008,
 "date": "2024-10-07"
},
{
 "price": 1.745233,
 "date": "2024-10-08"
},
{
 "price": 1.773865,
 "date": "2024-10-09"
},
{
 "price": 1.767697,
 "date": "2024-10-10"
},
{
 "price": 1.797358,
 "date": "2024-10-11"
},
{
 "price": 1.792848,
 "date": "2024-10-14"
},
{
 "price": 1.787863,
 "date": "2024-10-15"
},
{
 "price": 1.798908,
 "date": "2024-10-16"
},
{
 "price": 1.755566,
 "date": "2024-10-17"
},
{
 "price": 1.767388,
 "date": "2024-10-18"
},
{
 "price": 1.749904,
 "date": "2024-10-21"
},
{
 "price": 1.72387,
 "date": "2024-10-22"
},
{
 "price": 1.71896,
 "date": "2024-10-24"
},
{
 "price": 1.721559,
 "date": "2024-10-25"
},
{
 "price": 1.723148,
 "date": "2024-10-28"
},
{
 "price": 1.747424,
 "date": "2024-10-29"
},
{
 "price": 1.724455,
 "date": "2024-10-30"
},
{
 "price": 1.705795,
 "date": "2024-10-31"
},
{
 "price": 1.740208,
 "date": "2024-11-04"
},
{
 "price": 1.727025,
 "date": "2024-11-05"
},
{
 "price": 1.735892,
 "date": "2024-11-06"
},
{
 "price": 1.780005,
 "date": "2024-11-07"
},
{
 "price": 1.770244,
 "date": "2024-11-08"
},
{
 "price": 1.741572,
 "date": "2024-11-12"
},
{
 "price": 1.726667,
 "date": "2024-11-13"
},
{
 "price": 1.733857,
 "date": "2024-11-14"
},
{
 "price": 1.688214,
 "date": "2024-11-15"
},
{
 "price": 1.694862,
 "date": "2024-11-18"
},
{
 "price": 1.640305,
 "date": "2024-11-19"
},
{
 "price": 1.66289,
 "date": "2024-11-20"
},
{
 "price": 1.689771,
 "date": "2024-11-21"
},
{
 "price": 1.703943,
 "date": "2024-11-22"
},
{
 "price": 1.717445,
 "date": "2024-11-25"
},
{
 "price": 1.715639,
 "date": "2024-11-26"
},
{
 "price": 1.709642,
 "date": "2024-11-27"
},
{
 "price": 1.724637,
 "date": "2024-11-28"
},
{
 "price": 1.721228,
 "date": "2024-11-29"
},
{
 "price": 1.772576,
 "date": "2024-12-02"
},
{
 "price": 1.766539,
 "date": "2024-12-03"
},
{
 "price": 1.785542,
 "date": "2024-12-04"
},
{
 "price": 1.816645,
 "date": "2024-12-05"
},
{
 "price": 1.817331,
 "date": "2024-12-06"
},
{
 "price": 1.817284,
 "date": "2024-12-09"
},
{
 "price": 1.81581,
 "date": "2024-12-10"
},
{
 "price": 1.799882,
 "date": "2024-12-11"
},
{
 "price": 1.774592,
 "date": "2024-12-12"
},
{
 "price": 1.777499,
 "date": "2024-12-13"
},
{
 "price": 1.77563,
 "date": "2024-12-16"
},
{
 "price": 1.729934,
 "date": "2024-12-17"
},
{
 "price": 1.743353,
 "date": "2024-12-18"
},
{
 "price": 1.763849,
 "date": "2024-12-19"
},
{
 "price": 1.745831,
 "date": "2024-12-20"
},
{
 "price": 1.74879,
 "date": "2024-12-23"
},
{
 "price": 1.716372,
 "date": "2024-12-31"
},
{
 "price": 1.751,
 "date": "2025-01-02"
},
{
 "price": 1.77053,
 "date": "2025-01-03"
},
{
 "price": 1.799108,
 "date": "2025-01-07"
},
{
 "price": 1.77064,
 "date": "2025-01-08"
},
{
 "price": 1.772029,
 "date": "2025-01-09"
},
{
 "price": 1.781038,
 "date": "2025-01-10"
},
{
 "price": 1.754989,
 "date": "2025-01-13"
},
{
 "price": 1.757876,
 "date": "2025-01-14"
},
{
 "price": 1.79249,
 "date": "2025-01-15"
},
{
 "price": 1.784864,
 "date": "2025-01-16"
},
{
 "price": 1.80881,
 "date": "2025-01-17"
},
{
 "price": 1.822951,
 "date": "2025-01-20"
},
{
 "price": 1.827217,
 "date": "2025-01-21"
},
{
 "price": 1.853669,
 "date": "2025-01-22"
},
{
 "price": 1.85894,
 "date": "2025-01-23"
},
{
 "price": 1.868297,
 "date": "2025-01-24"
},
{
 "price": 1.861,
 "date": "2025-01-27"
},
{
 "price": 1.883396,
 "date": "2025-01-28"
},
{
 "price": 1.879553,
 "date": "2025-01-29"
},
{
 "price": 1.910965,
 "date": "2025-01-30"
},
{
 "price": 1.90409,
 "date": "2025-01-31"
},
{
 "price": 1.871327,
 "date": "2025-02-03"
},
{
 "price": 1.885268,
 "date": "2025-02-04"
},
{
 "price": 1.869337,
 "date": "2025-02-05"
},
{
 "price": 1.92196,
 "date": "2025-02-06"
},
{
 "price": 1.938068,
 "date": "2025-02-07"
},
{
 "price": 1.955818,
 "date": "2025-02-10"
},
{
 "price": 1.970931,
 "date": "2025-02-11"
},
{
 "price": 1.990652,
 "date": "2025-02-12"
},
{
 "price": 2.008493,
 "date": "2025-02-13"
},
{
 "price": 1.995422,
 "date": "2025-02-14"
},
{
 "price": 2.015674,
 "date": "2025-02-17"
},
{
 "price": 2.068553,
 "date": "2025-02-18"
},
{
 "price": 2.039766,
 "date": "2025-02-19"
},
{
 "price": 2.021923,
 "date": "2025-02-20"
},
{
 "price": 2.036197,
 "date": "2025-02-21"
},
{
 "price": 1.986877,
 "date": "2025-02-24"
},
{
 "price": 2.001072,
 "date": "2025-02-25"
},
{
 "price": 2.028945,
 "date": "2025-02-26"
},
{
 "price": 2.006742,
 "date": "2025-02-27"
},
{
 "price": 1.992644,
 "date": "2025-02-28"
},
{
 "price": 2.003577,
 "date": "2025-03-03"
},
{
 "price": 1.924949,
 "date": "2025-03-04"
},
{
 "price": 1.991812,
 "date": "2025-03-05"
},
{
 "price": 2.0272,
 "date": "2025-03-06"
},
{
 "price": 2.022736,
 "date": "2025-03-07"
},
{
 "price": 1.983861,
 "date": "2025-03-10"
},
{
 "price": 1.983263,
 "date": "2025-03-11"
},
{
 "price": 2.013578,
 "date": "2025-03-12"
},
{
 "price": 2.050231,
 "date": "2025-03-13"
},
{
 "price": 2.110227,
 "date": "2025-03-14"
},
{
 "price": 2.123082,
 "date": "2025-03-17"
},
{
 "price": 2.131203,
 "date": "2025-03-18"
},
{
 "price": 2.116129,
 "date": "2025-03-19"
},
{
 "price": 2.098091,
 "date": "2025-03-20"
},
{
 "price": 2.077319,
 "date": "2025-03-21"
},
{
 "price": 2.109997,
 "date": "2025-03-24"
},
{
 "price": 2.14677,
 "date": "2025-03-25"
},
{
 "price": 2.131148,
 "date": "2025-03-26"
},
{
 "price": 2.128283,
 "date": "2025-03-27"
},
{
 "price": 2.118541,
 "date": "2025-03-28"
},
{
 "price": 2.072194,
 "date": "2025-03-31"
},
{
 "price": 2.112529,
 "date": "2025-04-01"
},
{
 "price": 2.113427,
 "date": "2025-04-02"
},
{
 "price": 2.030441,
 "date": "2025-04-03"
},
{
 "price": 1.898675,
 "date": "2025-04-04"
},
{
 "price": 1.86315,
 "date": "2025-04-07"
},
{
 "price": 1.918874,
 "date": "2025-04-08"
},
{
 "price": 1.876588,
 "date": "2025-04-09"
},
{
 "price": 1.955746,
 "date": "2025-04-10"
},
{
 "price": 1.940515,
 "date": "2025-04-11"
},
{
 "price": 2.010935,
 "date": "2025-04-14"
},
{
 "price": 2.018996,
 "date": "2025-04-15"
},
{
 "price": 1.998491,
 "date": "2025-04-16"
},
{
 "price": 2.021522,
 "date": "2025-04-17"
},
{
 "price": 2.075353,
 "date": "2025-04-22"
},
{
 "price": 2.127132,
 "date": "2025-04-23"
},
{
 "price": 2.136763,
 "date": "2025-04-24"
},
{
 "price": 2.138104,
 "date": "2025-04-25"
},
{
 "price": 2.134923,
 "date": "2025-04-28"
},
{
 "price": 2.137408,
 "date": "2025-04-29"
},
{
 "price": 2.084024,
 "date": "2025-04-30"
},
{
 "price": 2.116307,
 "date": "2025-05-05"
},
{
 "price": 2.085081,
 "date": "2025-05-06"
},
{
 "price": 2.105893,
 "date": "2025-05-07"
},
{
 "price": 2.121489,
 "date": "2025-05-08"
},
{
 "price": 2.187224,
 "date": "2025-05-09"
},
{
 "price": 2.195663,
 "date": "2025-05-12"
},
{
 "price": 2.201787,
 "date": "2025-05-13"
},
{
 "price": 2.188604,
 "date": "2025-05-14"
},
{
 "price": 2.175599,
 "date": "2025-05-15"
},
{
 "price": 2.168639,
 "date": "2025-05-16"
},
{
 "price": 2.132916,
 "date": "2025-05-19"
},
{
 "price": 2.15122,
 "date": "2025-05-20"
},
{
 "price": 2.130753,
 "date": "2025-05-21"
},
{
 "price": 2.114836,
 "date": "2025-05-22"
},
{
 "price": 2.095426,
 "date": "2025-05-23"
},
{
 "price": 2.151107,
 "date": "2025-05-26"
},
{
 "price": 2.172343,
 "date": "2025-05-27"
},
{
 "price": 2.185386,
 "date": "2025-05-28"
},
{
 "price": 2.156539,
 "date": "2025-05-29"
},
{
 "price": 2.137459,
 "date": "2025-05-30"
},
{
 "price": 2.11587,
 "date": "2025-06-02"
},
{
 "price": 2.094985,
 "date": "2025-06-03"
},
{
 "price": 2.117494,
 "date": "2025-06-04"
},
{
 "price": 2.095605,
 "date": "2025-06-05"
},
{
 "price": 2.067428,
 "date": "2025-06-06"
},
{
 "price": 2.134667,
 "date": "2025-06-10"
},
{
 "price": 2.118608,
 "date": "2025-06-11"
},
{
 "price": 2.10488,
 "date": "2025-06-12"
},
{
 "price": 2.075806,
 "date": "2025-06-13"
},
{
 "price": 2.080054,
 "date": "2025-06-16"
},
{
 "price": 2.089483,
 "date": "2025-06-17"
},
{
 "price": 2.091729,
 "date": "2025-06-18"
},
{
 "price": 2.093863,
 "date": "2025-06-20"
},
{
 "price": 2.067631,
 "date": "2025-06-23"
},
{
 "price": 2.1165,
 "date": "2025-06-24"
},
{
 "price": 2.106671,
 "date": "2025-06-25"
},
{
 "price": 2.150836,
 "date": "2025-06-26"
},
{
 "price": 2.15736,
 "date": "2025-06-27"
},
{
 "price": 2.176289,
 "date": "2025-06-30"
},
{
 "price": 2.162852,
 "date": "2025-07-01"
},
{
 "price": 2.167173,
 "date": "2025-07-02"
},
{
 "price": 2.197959,
 "date": "2025-07-03"
},
{
 "price": 2.182568,
 "date": "2025-07-04"
},
{
 "price": 2.183659,
 "date": "2025-07-07"
},
{
 "price": 2.204437,
 "date": "2025-07-08"
},
{
 "price": 2.219828,
 "date": "2025-07-09"
},
{
 "price": 2.176395,
 "date": "2025-07-10"
},
{
 "price": 2.180444,
 "date": "2025-07-11"
},
{
 "price": 2.194101,
 "date": "2025-07-14"
},
{
 "price": 2.19412,
 "date": "2025-07-15"
},
{
 "price": 2.191188,
 "date": "2025-07-16"
},
{
 "price": 2.214444,
 "date": "2025-07-17"
},
{
 "price": 2.256333,
 "date": "2025-07-18"
},
{
 "price": 2.249819,
 "date": "2025-07-21"
},
{
 "price": 2.233095,
 "date": "2025-07-22"
},
{
 "price": 2.244876,
 "date": "2025-07-23"
},
{
 "price": 2.255685,
 "date": "2025-07-24"
},
{
 "price": 2.242205,
 "date": "2025-07-25"
},
{
 "price": 2.207535,
 "date": "2025-07-28"
},
{
 "price": 2.240458,
 "date": "2025-07-29"
},
{
 "price": 2.259715,
 "date": "2025-07-30"
},
{
 "price": 2.247232,
 "date": "2025-07-31"
},
{
 "price": 2.192025,
 "date": "2025-08-01"
},
{
 "price": 2.199393,
 "date": "2025-08-04"
},
{
 "price": 2.196623,
 "date": "2025-08-05"
},
{
 "price": 2.23428,
 "date": "2025-08-06"
},
{
 "price": 2.276612,
 "date": "2025-08-07"
},
{
 "price": 2.297594,
 "date": "2025-08-08"
},
{
 "price": 2.275081,
 "date": "2025-08-11"
},
{
 "price": 2.288504,
 "date": "2025-08-12"
},
{
 "price": 2.28606,
 "date": "2025-08-13"
},
{
 "price": 2.254599,
 "date": "2025-08-14"
},
{
 "price": 2.267434,
 "date": "2025-08-18"
},
{
 "price": 2.288287,
 "date": "2025-08-19"
},
{
 "price": 2.311689,
 "date": "2025-08-21"
},
{
 "price": 2.206908,
 "date": "2025-08-22"
},
{
 "price": 2.2321,
 "date": "2025-08-25"
},
{
 "price": 2.233969,
 "date": "2025-08-26"
},
{
 "price": 2.191863,
 "date": "2025-08-27"
},
{
 "price": 2.176409,
 "date": "2025-08-28"
},
{
 "price": 2.149204,
 "date": "2025-08-29"
},
{
 "price": 2.128175,
 "date": "2025-09-01"
},
{
 "price": 2.131101,
 "date": "2025-09-02"
},
{
 "price": 2.132114,
 "date": "2025-09-03"
},
{
 "price": 2.161287,
 "date": "2025-09-04"
},
{
 "price": 2.141263,
 "date": "2025-09-05"
},
{
 "price": 2.18364,
 "date": "2025-09-08"
},
{
 "price": 2.165645,
 "date": "2025-09-09"
},
{
 "price": 2.144967,
 "date": "2025-09-10"
},
{
 "price": 2.168638,
 "date": "2025-09-11"
},
{
 "price": 2.149741,
 "date": "2025-09-12"
},
{
 "price": 2.167296,
 "date": "2025-09-15"
},
{
 "price": 2.132672,
 "date": "2025-09-16"
},
{
 "price": 2.124312,
 "date": "2025-09-17"
},
{
 "price": 2.11557,
 "date": "2025-09-18"
},
{
 "price": 2.113165,
 "date": "2025-09-19"
},
{
 "price": 2.111555,
 "date": "2025-09-22"
},
{
 "price": 2.125154,
 "date": "2025-09-23"
},
{
 "price": 2.139587,
 "date": "2025-09-24"
},
{
 "price": 2.125014,
 "date": "2025-09-25"
},
{
 "price": 2.150915,
 "date": "2025-09-26"
},
{
 "price": 2.143801,
 "date": "2025-09-29"
},
{
 "price": 2.143144,
 "date": "2025-09-30"
},
{
 "price": 2.153577,
 "date": "2025-10-01"
},
{
 "price": 2.164081,
 "date": "2025-10-02"
},
{
 "price": 2.162412,
 "date": "2025-10-03"
},
{
 "price": 2.145063,
 "date": "2025-10-06"
},
{
 "price": 2.182255,
 "date": "2025-10-07"
},
{
 "price": 2.192926,
 "date": "2025-10-08"
},
{
 "price": 2.186786,
 "date": "2025-10-09"
},
{
 "price": 2.171359,
 "date": "2025-10-10"
},
{
 "price": 2.176541,
 "date": "2025-10-13"
},
{
 "price": 2.152331,
 "date": "2025-10-14"
},
{
 "price": 2.180183,
 "date": "2025-10-15"
},
{
 "price": 2.169379,
 "date": "2025-10-16"
},
{
 "price": 2.161294,
 "date": "2025-10-17"
},
{
 "price": 2.197,
 "date": "2025-10-20"
},
{
 "price": 2.194877,
 "date": "2025-10-21"
},
{
 "price": 2.225759,
 "date": "2025-10-22"
},
{
 "price": 2.243853,
 "date": "2025-10-27"
},
{
 "price": 2.280767,
 "date": "2025-10-28"
},
{
 "price": 2.276901,
 "date": "2025-10-29"
},
{
 "price": 2.266141,
 "date": "2025-10-30"
},
{
 "price": 2.230306,
 "date": "2025-10-31"
},
{
 "price": 2.23782,
 "date": "2025-11-03"
},
{
 "price": 2.226287,
 "date": "2025-11-04"
}
]