[
{
 "price": 1.0,
 "date": "2025-05-29"
},
{
 "price": 0.999692,
 "date": "2025-05-30"
},
{
 "price": 0.997939,
 "date": "2025-06-02"
},
{
 "price": 0.997901,
 "date": "2025-06-03"
},
{
 "price": 1.000725,
 "date": "2025-06-04"
},
{
 "price": 1.000226,
 "date": "2025-06-05"
},
{
 "price": 0.999544,
 "date": "2025-06-06"
},
{
 "price": 1.001549,
 "date": "2025-06-10"
},
{
 "price": 1.000191,
 "date": "2025-06-11"
},
{
 "price": 0.999682,
 "date": "2025-06-12"
},
{
 "price": 0.998011,
 "date": "2025-06-13"
},
{
 "price": 0.998246,
 "date": "2025-06-16"
},
{
 "price": 0.998557,
 "date": "2025-06-17"
},
{
 "price": 1.000595,
 "date": "2025-06-18"
},
{
 "price": 0.997259,
 "date": "2025-06-19"
},
{
 "price": 0.998393,
 "date": "2025-06-20"
},
{
 "price": 0.999432,
 "date": "2025-06-23"
},
{
 "price": 0.999459,
 "date": "2025-06-24"
},
{
 "price": 0.999015,
 "date": "2025-06-25"
},
{
 "price": 0.999493,
 "date": "2025-06-26"
},
{
 "price": 0.9994,
 "date": "2025-06-27"
},
{
 "price": 0.999086,
 "date": "2025-06-30"
},
{
 "price": 0.998949,
 "date": "2025-07-01"
},
{
 "price": 0.999069,
 "date": "2025-07-02"
},
{
 "price": 1.003331,
 "date": "2025-07-03"
},
{
 "price": 1.002595,
 "date": "2025-07-04"
}
]